Workbook

Sheet Raw_data
A1: Order_ID | B1: Order_Date | C1: Customer_ID | D1: Product_ID | E1: Product_Name | F1: Category | G1: Region | H1: City | I1: Quantity | J1: Unit_Price | K1: Discount | L1: Sales_Amount | M1: Sales_Channel | N1: Payment_Method | O1: Order_Status | P1: Salesperson | R1: Total Records | S1: =COUNTA(A2:A1529) -> 1528
A2: ORD50001 | B2: 45373 | C2: CUST1224 | D2: P012 | E2: Water Bottle | F2: Accessories | G2: East | H2: Kolkata | I2: 3 | J2: 876.84 | K2: 0.08 | L2: 2420.08 | M2: Online | N2: Debit Card | O2: Returned | P2: Arjun | R2: Total Colums | S2: 16
A3: ORD50002 | B3: 45986 | C3: CUST1131 | D3: P011 | E3: Headphones | F3: Electronics | G3: West | H3: Pune | I3: 3 | J3: 3174.6 | K3: 0 | L3: 9523.8 | M3: Online | N3: Cash on Delivery | O3: Cancelled | P3: Arjun | R3: Missing Customer ID | S3: =COUNTBLANK(C2:C1529) -> 35
A4: ORD50003 | B4: 45659 | C4: CUST1060 | D4: P013 | E4: Desk Lamp | F4: Furniture | G4: East | H4: Ranchi | I4: 3 | J4: 1613.97 | K4: 0.08 | L4: 4454.56 | M4: Online | N4: Cash on Delivery | O4: Cancelled | P4: Rahul | R4: Missing Cities | S4: =COUNTBLANK(H2:H1529) -> 22
A5: ORD50004 | B5: 45868 | C5: CUST1116 | D5: P003 | E5: Keyboard | F5: Electronics | G5: West | H5: Surat | I5: 4 | J5: 1935.56 | K5: 0.05 | L5: 7355.13 | M5: Marketplace | N5: Net Banking | O5: Cancelled | P5: Priya | R5: Missing Quantities | S5: =COUNTBLANK(I2:I1529) -> 12
A6: ORD50005 | B6: 45623 | C6: CUST1041 | D6: P008 | E6: Pen Set | F6: Stationery | G6: South | H6: Chennai | I6: 1 | J6: 226.44 | K6: 0.08 | L6: 208.32 | M6: Marketplace | N6: Credit Card | O6: Returned | P6: Sneha | R6: Missing Discounts | S6: =COUNTBLANK(K2:K1529) -> 10
A7: ORD50006 | B7: 45589 | C7: CUST1121 | D7: P014 | E7: Webcam | F7: Electronics | G7: South | H7: Hyderabad | I7: 1 | J7: 2660.88 | K7: 0.08 | L7: 2448.01 | M7: Marketplace | N7: Debit Card | O7: Completed | P7: Priya | R7: Missing Payment Method | S7: =COUNTBLANK(N2:N1529) -> 18
A8: ORD50007 | B8: 45806 | C8: CUST1217 | D8: P011 | E8: Headphones | F8: Electronics | G8: West | H8: Mumbai | I8: 3 | J8: 3302.54 | K8: 0.03 | L8: 9610.39 | M8: Online | N8: Net Banking | O8: Cancelled | P8: Sneha | R8: Missing Salesperosns | S8: =COUNTBLANK(P2:P1529) -> 15
A9: ORD50008 | B9: 46025 | C9: CUST1166 | D9: P013 | E9: Desk Lamp | F9: Furniture | G9: South | H9: Hyderabad | I9: 5 | J9: 1646.72 | K9: 0.05 | L9: 7821.92 | M9: Marketplace | N9: UPI | O9: Cancelled | P9: Anil
A10: ORD50009 | B10: 46018 | C10: CUST1184 | D10: P012 | E10: Water Bottle | F10: Accessories | G10: West | H10: Ahmedabad | I10: 4 | J10: 888.18 | K10: 0.08 | L10: 3268.5 | M10: Store | N10: Debit Card | O10: Completed | P10: Anil
A11: ORD50010 | B11: 45419 | C11: CUST1223 | D11: P004 | E11: Monitor 24-inch | F11: Electronics | G11: North | H11: Lucknow | I11: 3 | J11: 12442.19 | K11: 0.1 | L11: 33593.91 | M11: Online | N11: Net Banking | O11: Completed | P11: Arjun
A12: ORD50011 | B12: 45807 | C12: CUST1080 | D12: P009 | E12: Backpack | F12: Accessories | G12: North | H12: Jaipur | I12: 3 | J12: 1664.88 | K12: 0.15 | L12: 4245.44 | M12: Store | N12: Cash on Delivery | O12: Completed | P12: Rahul
A13: ORD50012 | B13: 45664 | C13: CUST1223 | D13: P015 | E13: Phone Stand | F13: Accessories | G13: West | H13: Pune | I13: 1 | J13: 650.53 | K13: 0.03 | L13: 631.01 | M13: Marketplace | N13: Credit Card | O13: Completed | P13: Arjun
A14: ORD50013 | B14: 45407 | C14: CUST1173 | D14: P009 | E14: Backpack | F14: Accessories | G14: East | H14: Bhubaneswar | I14: 4 | J14: 1773.04 | K14: 0.2 | L14: 5673.73 | M14: Marketplace | N14: Credit Card | O14: Completed | P14: Rahul
A15: ORD50014 | B15: 45312 | C15: CUST1187 | D15: P002 | E15: Wireless Mouse | F15: Electronics | G15: North | H15: Delhi | I15: 4 | J15: 1192.68 | K15: 0.15 | L15: 4055.11 | M15: Marketplace | N15: Debit Card | O15: Returned | P15: Priya
A16: ORD50015 | B16: 45745 | C16: CUST1100 | D16: P011 | E16: Headphones | F16: Electronics | G16: South | H16: Bengaluru | I16: 3 | J16: 3098.37 | K16: 0.03 | L16: 9016.26 | M16: Store | N16: Net Banking | O16: Completed | P16: Vikram
A17: ORD50016 | B17: 45371 | C17: CUST1129 | D17: P006 | E17: Desk | F17: Furniture | G17: North | H17: Lucknow | I17: 2 | J17: 7670.68 | K17: 0.2 | L17: 12273.09 | M17: Store | N17: Credit Card | O17: Cancelled | P17: Vikram
A18: ORD50017 | B18: 45532 | C18: CUST1117 | D18: P012 | E18: Water Bottle | F18: Accessories | G18: South | H18: Hyderabad | I18: 4 | J18: 819.02 | K18: 0.15 | L18: 2784.67 | M18: Online | N18: Debit Card | O18: Returned | P18: Priya
A19: ORD50018 | B19: 45707 | C19: CUST1143 | D19: P011 | E19: Headphones | F19: Electronics | G19: North | H19: Delhi | I19: 4 | J19: 3240.56 | K19: 0.05 | L19: 12314.13 | M19: Store | N19: Cash on Delivery | O19: Completed | P19: Meena
A20: ORD50019 | B20: 45741 | C20: CUST1164 | D20: P011 | E20: Headphones | F20: Electronics | G20: East | H20: Kolkata | I20: 3 | J20: 3243.06 | K20: 0.05 | L20: 9242.72 | M20: Store | N20: Net Banking | O20: Completed | P20: Meena
... A31: ORD50030 | B31: 45973 | C31: CUST1009 | D31: P006 | E31: Desk | F31: Furniture | G31: South | H31: Hyderabad | I31: 1 | J31: 6901.6 | K31: 0.2 | L31: 5521.28 | M31: Online | N31: Cash on Delivery | O31: Returned | P31: Priya
A32: ORD50031 | B32: 45973 | D32: P003 | E32: Keyboard | F32: Electronics | G32: South | H32: Visakhapatnam | I32: 3 | J32: 1712.57 | K32: 0.15 | L32: 4367.05 | M32: Online | N32: Cash on Delivery | O32: Cancelled | P32: Rahul
A33: ORD50032 | B33: 46178 | D33: P008 | E33: Pen Set | F33: Stationery | G33: East | H33: Kolkata | I33: 3 | J33: 202.89 | K33: 0.03 | L33: 590.41 | M33: Online | N33: UPI | O33: Completed | P33: Arjun
A34: ORD50033 | B34: 46176 | C34: CUST1181 | D34: P002 | E34: Wireless Mouse | F34: Electronics | G34: South | H34: Visakhapatnam | I34: 0 | J34: 1215.57 | K34: 0.2 | L34: 2917.37 | M34: Online | N34: Cash on Delivery | O34: Cancelled | P34: Anil
A35: ORD50034 | B35: 45944 | C35: CUST1148 | D35: P002 | E35: Wireless Mouse | F35: Electronics | G35: East | H35: Ranchi | I35: 5 | J35: 1127.76 | K35: 0 | L35: 5638.8 | M35: Online | N35: Credit Card | O35: Returned | P35: Rahul
A36: ORD50035 | B36: 45412 | C36: CUST1249 | D36: P008 | E36: Pen Set | F36: Stationery | G36: East | H36: Ranchi | I36: 4 | J36: 212.48 | K36: 0.05 | L36: 807.42 | M36: Marketplace | N36: Debit Card | O36: Completed | P36: Kiran
A37: ORD50036 | B37: 45798 | C37: CUST1195 | D37: P003 | E37: Keyboard | F37: Electronics | G37: East | H37: Bhubaneswar | I37: 5 | J37: 1696.42 | K37: 0 | L37: 8482.1 | M37: Online | N37: Cash on Delivery | O37: Completed | P37: Kiran
A38: ORD50037 | B38: 45457 | C38: CUST1122 | D38: P014 | E38: Webcam | F38: Electronics | G38: East | H38: Ranchi | I38: 5 | J38: 2927.57 | K38: 0.08 | L38: 13466.82 | M38: Online | N38: Net Banking | O38: Completed | P38: Rahul
A39: ORD50038 | B39: 46048 | C39: CUST1199 | D39: P004 | E39: Monitor 24-inch | F39: Electronics | G39: West | H39: Ahmedabad | I39: 3 | J39: 12561.54 | K39: 0.03 | L39: 36554.08 | M39: Marketplace | N39: Cash on Delivery | O39: Cancelled | P39: Kiran
A40: ORD50039 | B40: 45556 | C40: CUST1111 | D40: P007 | E40: Notebook Pack | F40: Stationery | G40: North | H40: Chandigarh | I40: 2 | J40: 460.94 | K40: 0.2 | L40: 737.5 | M40: Marketplace | N40: Credit Card | O40: Completed | P40: Kiran
A41: ORD50040 | B41: 45518 | C41: CUST1250 | D41: P005 | E41: Office Chair | F41: Furniture | G41: North | H41: Delhi | I41: 5 | J41: 9981.18 | K41: 0.15 | L41: 42420.01 | M41: Marketplace | N41: UPI | O41: Completed | P41: Kiran
A42: ORD50041 | B42: 45618 | C42: CUST1081 | D42: P003 | E42: Keyboard | F42: Electronics | G42: North | H42: Chandigarh | I42: 5 | J42: 1697.44 | K42: 0.05 | L42: 8062.84 | M42: Marketplace | N42: Debit Card | O42: Completed | P42: Priya
A43: ORD50042 | B43: 45551 | C43: CUST1185 | D43: P009 | E43: Backpack | F43: Accessories | G43: North | H43: Delhi | I43: 3 | J43: 1662.09 | K43: 0 | L43: 4986.27 | M43: Online | N43: UPI | O43: Cancelled | P43: Anil
A44: ORD50043 | B44: 45683 | C44: CUST1103 | D44: P009 | E44: Backpack | F44: Accessories | G44: East | H44: Ranchi | I44: 4 | J44: 1747.58 | K44: 0.15 | L44: 5941.77 | M44: Store | N44: Net Banking | O44: Returned | P44: Meena
A45: ORD50044 | B45: 46068 | C45: CUST1060 | D45: P009 | E45: Backpack | F45: Accessories | G45: North | H45: Delhi | I45: 3 | J45: 1724.18 | K45: 0.03 | L45: 5017.36 | M45: Store | N45: Debit Card | O45: Returned | P45: Sneha
... A54: ORD50053 | B54: 45821 | C54: CUST1036 | D54: P002 | E54: Wireless Mouse | F54: Electronics | G54: East | H54: Kolkata | I54: 5 | J54: 1288.11 | K54: 0.15 | L54: 5474.47 | M54: Marketplace | N54: Debit Card | O54: Completed | P54: Sneha
A55: ORD50054 | B55: 46005 | C55: CUST1188 | D55: P015 | E55: Phone Stand | F55: Accessories | G55: West | I55: 5 | J55: 672.38 | K55: 0.2 | L55: 2689.52 | M55: Online | N55: UPI | O55: Completed | P55: Kiran
A56: ORD50055 | B56: 45444 | C56: CUST1149 | D56: P003 | E56: Keyboard | F56: Electronics | G56: North | H56: Lucknow | I56: 3 | J56: 1790.2 | L56: 5370.6 | M56: Store | N56: Net Banking | O56: Cancelled | P56: Vikram
A57: ORD50056 | B57: 46020 | C57: CUST1220 | D57: P008 | E57: Pen Set | F57: Stationery | G57: South | H57: Hyderabad | I57: 2 | J57: 235.18 | K57: 0.1 | L57: 423.32 | M57: Marketplace | N57: UPI | O57: Cancelled | P57: Anil
A58: ORD50057 | B58: 45737 | C58: CUST1202 | D58: P010 | E58: USB-C Hub | F58: Electronics | G58: East | H58: Patna | I58: 3 | J58: 2260.27 | K58: 0.2 | L58: 5424.65 | M58: Store | N58: Net Banking | O58: Returned | P58: Meena
A59: ORD50058 | B59: 45987 | D59: P010 | E59: USB-C Hub | F59: Electronics | G59: South | H59: Hyderabad | I59: 4 | J59: 2134.68 | K59: 0.05 | L59: 8111.78 | M59: Marketplace | O59: Completed | P59: Vikram
A60: ORD50059 | B60: 45798 | C60: CUST1190 | D60: P007 | E60: Notebook Pack | F60: Stationery | G60: East | H60: Ranchi | I60: 2 | J60: 453.82 | K60: 0 | L60: 907.64 | M60: Marketplace | N60: Credit Card | O60: Cancelled | P60: Kiran
A61: ORD50060 | B61: 45729 | C61: CUST1221 | D61: P003 | E61: Keyboard | F61: Electronics | G61: South | H61: Chennai | I61: -2 | J61: 1862.71 | K61: 0.2 | L61: 5960.67 | M61: Store | N61: UPI | O61: Completed | P61: Meena
A62: ORD50061 | B62: 46092 | C62: CUST1153 | D62: P010 | E62: USB-C Hub | F62: Electronics | G62: North | H62: Lucknow | I62: 1 | J62: 2265.51 | K62: 0.08 | L62: 2084.27 | M62: Online | N62: UPI | O62: Completed | P62: Arjun
A63: ORD50062 | B63: 46044 | C63: CUST1004 | D63: P007 | E63: Notebook Pack | F63: Stationery | G63: South | H63: Visakhapatnam | I63: 5 | J63: 445.85 | K63: 0.08 | L63: 2050.91 | M63: Store | N63: Cash on Delivery | O63: Cancelled | P63: Meena
A64: ORD50063 | B64: 45788 | C64: CUST1229 | D64: P002 | E64: Wireless Mouse | F64: Electronics | G64: South | H64: Chennai | I64: 5 | J64: 1158.51 | K64: 0 | L64: 5792.55 | M64: Marketplace | N64: UPI | O64: Completed | P64: Arjun
A65: ORD50064 | B65: 46203 | C65: CUST1177 | D65: P001 | E65: Laptop 15-inch | F65: Electronics | G65: East | H65: Ranchi | I65: 1 | J65: 60740.58 | K65: 0.1 | L65: 54666.52 | M65: Marketplace | N65: UPI | O65: Completed | P65: Priya
A66: ORD50065 | B66: 45705 | C66: CUST1052 | D66: P003 | E66: Keyboard | F66: Electronics | G66: West | H66: Pune | I66: 4 | J66: 1918.26 | K66: 0.15 | L66: 6522.08 | M66: Store | N66: Cash on Delivery | O66: Completed | P66: Anil
A67: ORD50066 | B67: 45296 | C67: CUST1251 | D67: P003 | E67: Keyboard | F67: Electronics | G67: North | H67: Delhi | I67: 5 | J67: 1886.83 | K67: 0.1 | L67: 8490.74 | M67: Online | N67: Cash on Delivery | O67: Completed | P67: Anil
A68: ORD50067 | B68: 45902 | C68: CUST1201 | D68: P013 | E68: Desk Lamp | F68: Furniture | G68: West | H68: Surat | I68: 5 | J68: 1650.72 | K68: 0 | L68: 8253.6 | M68: Marketplace | N68: Debit Card | O68: Completed | P68: Sneha
A69: ORD50068 | B69: 45476 | C69: CUST1143 | D69: P002 | E69: Wireless Mouse | F69: Electronics | G69: North | H69: Lucknow | I69: 4 | J69: 1247.08 | K69: 0.08 | L69: 4589.25 | M69: Online | N69: Cash on Delivery | O69: Completed | P69: Priya
A70: ORD50069 | B70: 46033 | C70: CUST1071 | D70: P012 | E70: Water Bottle | F70: Accessories | G70: North | I70: 1 | J70: 878.55 | K70: 0 | L70: 878.55 | M70: Marketplace | N70: Net Banking | O70: Completed | P70: Kiran
A71: ORD50070 | B71: 45341 | C71: CUST1120 | D71: P002 | E71: Wireless Mouse | F71: Electronics | G71: East | H71: Patna | I71: 1 | J71: 1273.76 | K71: 0 | L71: 1273.76 | M71: Store | N71: UPI | O71: Completed | P71: Anil
A72: ORD50071 | B72: 45994 | C72: CUST1120 | D72: P003 | E72: Keyboard | F72: Electronics | G72: South | H72: Visakhapatnam | I72: 5 | J72: 1881.82 | K72: 0.1 | L72: 8468.19 | M72: Store | N72: Cash on Delivery | O72: Completed
A73: ORD50072 | B73: 45424 | C73: CUST1140 | D73: P004 | E73: Monitor 24-inch | F73: Electronics | G73: West | H73: Ahmedabad | I73: 3 | J73: 12656.03 | K73: 0.05 | L73: 36069.69 | M73: Online | N73: Net Banking | O73: Completed | P73: Vikram
A74: ORD50073 | B74: 45436 | C74: CUST1106 | D74: P003 | E74: Keyboard | F74: Electronics | G74: South | H74: Hyderabad | I74: 3 | J74: 1792.56 | K74: 0.1 | L74: 4839.91 | M74: Online | N74: Cash on Delivery | O74: Completed | P74: Vikram
A75: ORD50074 | B75: 45545 | C75: CUST1105 | D75: P002 | E75: Wireless Mouse | F75: Electronics | G75: South | H75: Bengaluru | I75: 4 | J75: 1221.31 | K75: 0.05 | L75: 4640.98 | M75: Marketplace | N75: Debit Card | O75: Completed | P75: Sneha
A76: ORD50075 | B76: 46058 | C76: CUST1083 | D76: P004 | E76: Monitor 24-inch | F76: Electronics | G76: West | H76: Pune | I76: 3 | J76: 11572.12 | K76: 0.1 | L76: 31244.72 | M76: Store | N76: Debit Card | O76: Completed | P76: Priya
A77: ORD50076 | B77: 45497 | C77: CUST1143 | D77: P002 | E77: Wireless Mouse | F77: Electronics | G77: East | H77: Patna | I77: 2 | J77: 1238.78 | K77: 0.08 | L77: 2279.36 | M77: Store | N77: Net Banking | O77: Completed | P77: Rahul
A78: ORD50077 | B78: 45516 | C78: CUST1113 | D78: P012 | E78: Water Bottle | F78: Accessories | G78: South | H78: Bengaluru | I78: 3 | J78: 867.14 | K78: 0.03 | L78: 2523.38 | M78: Store | N78: Cash on Delivery | O78: Completed | P78: Meena
A79: ORD50078 | B79: 45963 | C79: CUST1191 | D79: P009 | E79: Backpack | F79: Accessories | G79: West | I79: 1 | J79: 1801.05 | K79: 0.2 | L79: 1440.84 | M79: Online | N79: Net Banking | O79: Completed | P79: Rahul
A80: ORD50079 | B80: 45765 | C80: CUST1031 | D80: P013 | E80: Desk Lamp | F80: Furniture | G80: South | H80: Chennai | I80: 3 | J80: 1490.45 | K80: 0 | L80: 4471.35 | M80: Marketplace | N80: Cash on Delivery | O80: Completed | P80: Anil
A81: ORD50080 | B81: 45547 | C81: CUST1018 | D81: P009 | E81: Backpack | F81: Accessories | G81: South | H81: Bengaluru | I81: 3 | J81: 1746.4 | K81: 0.03 | L81: 5082.02 | M81: Marketplace | N81: UPI | O81: Completed | P81: Meena
A82: ORD50081 | B82: 45936 | C82: CUST1040 | D82: P013 | E82: Desk Lamp | F82: Furniture | G82: South | H82: Bengaluru | I82: 2 | J82: 1625.82 | K82: 0.1 | L82: 2926.48 | M82: Online | N82: Debit Card | O82: Completed | P82: Kiran
A83: ORD50082 | B83: 46166 | D83: P002 | E83: Wireless Mouse | F83: Electronics | G83: West | H83: Ahmedabad | I83: 3 | J83: 1163.7 | K83: 0.15 | L83: 2967.44 | M83: Online | N83: Net Banking | O83: Cancelled | P83: Sneha
A84: ORD50083 | B84: 46136 | C84: CUST1055 | D84: P010 | E84: USB-C Hub | F84: Electronics | G84: South | H84: Visakhapatnam | I84: 1 | J84: 2208.83 | K84: 0.1 | L84: 1987.95 | M84: Online | N84: Net Banking | O84: Completed | P84: Sneha
A85: ORD50084 | B85: 46054 | C85: CUST1209 | D85: P014 | E85: Webcam | F85: Electronics | G85: West | H85: Surat | I85: 5 | J85: 2951.9 | K85: 0.08 | L85: 13578.74 | M85: Store | N85: UPI | O85: Completed | P85: Sneha
A86: ORD50085 | B86: 46060 | C86: CUST1197 | D86: P006 | E86: Desk | F86: Furniture | G86: South | H86: Visakhapatnam | I86: 1 | J86: 7123.71 | K86: 0.15 | L86: 6055.15 | M86: Store | O86: Completed | P86: Rahul
A87: ORD50086 | B87: 45457 | C87: CUST1051 | D87: P004 | E87: Monitor 24-inch | F87: Electronics | G87: West | H87: Pune | I87: 5 | J87: 11965.7 | K87: 0 | L87: 59828.5 | M87: Online | O87: Returned | P87: Kiran
A88: ORD50087 | B88: 45951 | C88: CUST1064 | D88: P008 | E88: Pen Set | F88: Stationery | G88: North | H88: Chandigarh | I88: 1 | J88: 232.09 | K88: 0.03 | L88: 225.13 | M88: Store | N88: Debit Card | O88: Completed | P88: Sneha
A89: ORD50088 | B89: 45903 | C89: CUST1194 | D89: P012 | E89: Water Bottle | F89: Accessories | G89: West | H89: Ahmedabad | I89: 4 | J89: 831.86 | K89: 0 | L89: 3327.44 | M89: Marketplace | N89: Credit Card | O89: Returned | P89: Meena
A90: ORD50089 | B90: 45593 | C90: CUST1222 | D90: P008 | E90: Pen Set | F90: Stationery | G90: east | H90: Bhubaneswar | I90: 4 | J90: 220.17 | K90: 0.1 | L90: 792.61 | M90: Marketplace | N90: Credit Card | O90: Completed | P90: Anil
A91: ORD50090 | B91: 46067 | D91: P006 | E91: Desk | F91: Furniture | G91: South | H91: Hyderabad | I91: 3 | J91: 7236.19 | K91: 0.08 | L91: 19971.88 | M91: Online | N91: Credit Card | O91: Returned | P91: Vikram
A92: ORD50091 | B92: 45865 | C92: CUST1089 | D92: P010 | E92: USB-C Hub | F92: Electronics | G92: South | H92: Visakhapatnam | I92: 1 | J92: 2091.44 | K92: 0 | L92: 2091.44 | M92: Online | N92: Net Banking | O92: Returned | P92: Arjun
A93: ORD50092 | B93: 45700 | C93: CUST1109 | D93: P007 | E93: Notebook Pack | F93: Stationery | G93: south | H93: Visakhapatnam | I93: 1 | J93: 414.53 | K93: 0.1 | L93: 373.08 | M93: Online | N93: Net Banking | O93: Completed | P93: Arjun
A94: ORD50093 | B94: 45942 | C94: CUST1125 | D94: P015 | E94: Phone Stand | F94: Accessories | G94: West | H94: Ahmedabad | I94: 4 | J94: 729.28 | K94: 0.2 | L94: 2333.7 | M94: Marketplace | N94: Debit Card | O94: Cancelled | P94: Rahul
A95: ORD50094 | B95: 46170 | C95: CUST1132 | D95: P010 | E95: USB-C Hub | F95: Electronics | G95: West | H95: Ahmedabad | I95: 3 | J95: 2064.16 | K95: 0.2 | L95: 4953.98 | M95: Marketplace | N95: Debit Card | O95: Completed | P95: Kiran
A96: ORD50095 | B96: 46168 | C96: CUST1256 | D96: P010 | E96: USB-C Hub | F96: Electronics | G96: South | H96: Chennai | I96: 5 | J96: 2125.46 | K96: 0 | L96: 10627.3 | M96: Marketplace | N96: Cash on Delivery | O96: Cancelled | P96: Arjun
A97: ORD50096 | B97: 45608 | C97: CUST1251 | D97: P001 | E97: Laptop 15-inch | F97: Electronics | G97: North | H97: Jaipur | I97: 2 | J97: 67884.37 | K97: 0 | L97: 135768.74 | M97: Marketplace | N97: Cash on Delivery | O97: Returned | P97: Sneha
A98: ORD50097 | B98: 45588 | C98: CUST1207 | D98: P015 | E98: Phone Stand | F98: Accessories | G98: North | H98: Delhi | I98: 3 | J98: 653.5 | K98: 0 | L98: 1960.5 | M98: Store | N98: Debit Card | O98: Cancelled | P98: Rahul
A99: ORD50098 | B99: 46135 | C99: CUST1248 | D99: P007 | E99: Notebook Pack | F99: Stationery | G99: West | H99: Mumbai | I99: 2 | J99: 440.83 | K99: 0 | L99: 881.66 | M99: Store | N99: UPI | O99: Returned | P99: Arjun
A100: ORD50099 | B100: 45987 | C100: CUST1226 | D100: P011 | E100: Headphones | F100: Electronics | G100: East | H100: Bhubaneswar | I100: 4 | J100: 3322.59 | K100: 0 | L100: 13290.36 | M100: Marketplace | N100: Credit Card | O100: Completed | P100: Vikram
A101: ORD50100 | B101: 45505 | C101: CUST1248 | D101: P002 | E101: Wireless Mouse | F101: Electronics | G101: East | H101: Patna | I101: 2 | J101: 1104.86 | K101: 0.2 | L101: 1767.78 | M101: Online | N101: Net Banking | O101: Completed | P101: Anil
A102: ORD50101 | B102: 45984 | C102: CUST1175 | D102: P007 | E102: Notebook Pack | F102: Stationery | G102: East | H102: Bhubaneswar | I102: 5 | J102: 431.11 | K102: 0.1 | L102: 1940 | M102: Marketplace | N102: Debit Card | O102: Completed | P102: Meena
A103: ORD50102 | B103: 46070 | C103: CUST1030 | D103: P014 | E103: Webcam | F103: Electronics | G103: South | H103: Visakhapatnam | I103: 4 | J103: 2753.83 | K103: 0.1 | L103: 9913.79 | M103: Store | N103: Cash on Delivery | O103: Returned | P103: Priya
... A113: ORD50112 | B113: 45686 | C113: CUST1077 | D113: P003 | E113: Keyboard | F113: Electronics | G113: North | H113: Delhi | I113: 5 | J113: 1685.66 | K113: 0.2 | L113: 6742.64 | M113: Online | N113: Credit Card | O113: Completed | P113: Anil
A114: ORD50113 | B114: 46189 | C114: CUST1082 | D114: P007 | E114: Notebook Pack | F114: Stationery | G114: South | H114: Chennai | J114: 417.67 | K114: 0.15 | L114: 1065.06 | M114: Online | N114: Net Banking | O114: Completed | P114: Meena
A115: ORD50114 | B115: 45347 | C115: CUST1128 | D115: P014 | E115: Webcam | F115: Electronics | G115: East | H115: Bhubaneswar | I115: 3 | J115: 2711.33 | K115: 0.03 | L115: 7889.97 | M115: Online | N115: Debit Card | O115: Completed | P115: Anil
A116: ORD50115 | B116: 45556 | C116: CUST1001 | D116: P002 | E116: Wireless Mouse | F116: Electronics | G116: South | H116: Visakhapatnam | I116: 5 | J116: 1201.57 | K116: 0.03 | L116: 5827.61 | M116: Store | N116: UPI | O116: Completed | P116: Sneha
A117: ORD50116 | B117: 45685 | D117: P009 | E117: Backpack | F117: Accessories | G117: West | H117: Pune | I117: 3 | J117: 1730.98 | K117: 0.15 | L117: 4414 | M117: Store | N117: Credit Card | O117: Returned | P117: Sneha
A118: ORD50117 | B118: 46079 | C118: CUST1086 | D118: P011 | E118: Headphones | F118: Electronics | G118: South | H118: Visakhapatnam | I118: 2 | J118: 3420.36 | K118: 0.15 | L118: 5814.61 | M118: Online | N118: Debit Card | O118: Completed | P118: Meena
A119: ORD50118 | B119: 45940 | C119: CUST1006 | D119: P003 | E119: Keyboard | F119: Electronics | G119: North | H119: Chandigarh | I119: 4 | J119: 1695.8 | K119: 0 | L119: 6783.2 | M119: Online | N119: UPI | O119: Returned | P119: Priya
A120: ORD50119 | B120: 46036 | C120: CUST1162 | D120: P001 | E120: Laptop 15-inch | F120: Electronics | G120: North | H120: Delhi | I120: 1 | J120: 62313.04 | K120: 0.1 | L120: 56081.74 | M120: Store | N120: Credit Card | O120: Completed | P120: Arjun
A121: ORD50120 | B121: 46066 | C121: CUST1120 | D121: P008 | E121: Pen Set | F121: Stationery | G121: North | H121: Delhi | I121: 2 | J121: 224.19 | K121: 0.15 | L121: 381.12 | M121: Marketplace | N121: Net Banking | O121: Returned | P121: Meena
A122: ORD50121 | B122: 45557 | C122: CUST1119 | D122: P004 | E122: Monitor 24-inch | F122: Electronics | G122: North | H122: Chandigarh | I122: 5 | J122: 12706.85 | K122: 0.08 | L122: 58451.51 | M122: Marketplace | N122: UPI | O122: Completed | P122: Arjun
A123: ORD50122 | B123: 46033 | C123: CUST1078 | D123: P003 | E123: Keyboard | F123: Electronics | G123: South | H123: Hyderabad | I123: 3 | J123: 1829.01 | K123: 0.15 | L123: 4663.98 | M123: Store | N123: Debit Card | O123: Completed | P123: Rahul
A124: ORD50123 | B124: 46042 | C124: CUST1091 | D124: P002 | E124: Wireless Mouse | F124: Electronics | G124: West | H124: Ahmedabad | I124: 1 | J124: 1107.65 | K124: 0.15 | L124: 941.5 | M124: Online | N124: Net Banking | O124: Cancelled | P124: Meena
A125: ORD50124 | B125: 45937 | C125: CUST1039 | D125: P005 | E125: Office Chair | F125: Furniture | G125: East | H125: Patna | I125: 5 | J125: 10092.83 | K125: 0.05 | L125: 47940.94 | M125: Online | N125: UPI | O125: Cancelled | P125: Priya
A126: ORD50125 | B126: 45903 | C126: CUST1132 | D126: P011 | E126: Headphones | F126: Electronics | G126: North | H126: Jaipur | I126: 1 | J126: 3451.79 | K126: 0.15 | L126: 2934.02 | M126: Online | N126: Cash on Delivery | O126: Completed | P126: Kiran
A127: ORD50126 | B127: 46197 | C127: CUST1024 | D127: P009 | E127: Backpack | F127: Accessories | G127: East | H127: Ranchi | I127: 2 | J127: 1914.42 | K127: 0 | L127: 3828.84 | M127: Store | N127: Debit Card | O127: Completed | P127: Kiran
...

Sheet Clean_data 
A1: Order_ID | B1: Order_Date | C1: Customer_ID | D1: Product_ID | E1: Product_Name | F1: Category | G1: Region | H1: City | I1: Quantity | J1: Unit_Price | K1: Discount | L1: Sales_Amount | M1: Sales_Channel | N1: Payment_Method | O1: Order_Status | P1: Salesperson | Q1: Order_Status_Clean | R1: Sales_Channel_Clean | S1: Payment_Method_Clean | T1: Category_Clean | U1: Quantity_Status | V1: Quantity_Review | W1: Discount_Status | X1: Gross_Sales | Y1: Net_Sales
A2: ORD50001 | B2: 45373 | C2: CUST1224 | D2: P012 | E2: Water Bottle | F2: Accessories | G2: East | H2: Kolkata | I2: 3 | J2: 876.84 | K2: 0.08 | L2: 2420.08 | M2: Online | N2: Debit Card | O2: Returned | P2: Arjun | Q2: =PROPER(O2) -> Returned | R2: =PROPER(M2) -> Online | S2: {=PROPER(N2:N1529)} -> Debit Card | T2: {=PROPER(F2:F1529)} -> Accessories | U2: =IF(I2<=0,"INVALID","VALID") -> VALID | V2: =IF(I2>100,"REVIEW","NORMAL") -> NORMAL | W2: =IF(OR(K2<0,K2>1),"Invalid","Valid") -> Valid | X2: =I2*J2 -> 2630.52 | Y2: =I2*J2-(I2*J2*K2) -> 2420.0784
A3: ORD50002 | B3: 45986 | C3: CUST1131 | D3: P011 | E3: Headphones | F3: Electronics | G3: West | H3: Pune | I3: 3 | J3: 3174.6 | K3: 0 | L3: 9523.8 | M3: Online | N3: Cash on Delivery | O3: Cancelled | P3: Arjun | Q3: =PROPER(O3) -> Cancelled | R3: =PROPER(M3) -> Online | S3: Cash On Delivery | T3: Electronics | U3: =IF(I3<=0,"INVALID","VALID") -> VALID | V3: =IF(I3>100,"REVIEW","NORMAL") -> NORMAL | W3: =IF(OR(K3<0,K3>1),"Invalid","Valid") -> Valid | X3: =I3*J3 -> 9523.8 | Y3: =I3*J3-(I3*J3*K3) -> 9523.8
A4: ORD50003 | B4: 45659 | C4: CUST1060 | D4: P013 | E4: Desk Lamp | F4: Furniture | G4: East | H4: Ranchi | I4: 3 | J4: 1613.97 | K4: 0.08 | L4: 4454.56 | M4: Online | N4: Cash on Delivery | O4: Cancelled | P4: Rahul | Q4: =PROPER(O4) -> Cancelled | R4: =PROPER(M4) -> Online | S4: Cash On Delivery | T4: Furniture | U4: =IF(I4<=0,"INVALID","VALID") -> VALID | V4: =IF(I4>100,"REVIEW","NORMAL") -> NORMAL | W4: =IF(OR(K4<0,K4>1),"Invalid","Valid") -> Valid | X4: =I4*J4 -> 4841.91 | Y4: =I4*J4-(I4*J4*K4) -> 4454.5572
A5: ORD50004 | B5: 45868 | C5: CUST1116 | D5: P003 | E5: Keyboard | F5: Electronics | G5: West | H5: Surat | I5: 4 | J5: 1935.56 | K5: 0.05 | L5: 7355.13 | M5: Marketplace | N5: Net Banking | O5: Cancelled | P5: Priya | Q5: =PROPER(O5) -> Cancelled | R5: =PROPER(M5) -> Marketplace | S5: Net Banking | T5: Electronics | U5: =IF(I5<=0,"INVALID","VALID") -> VALID | V5: =IF(I5>100,"REVIEW","NORMAL") -> NORMAL | W5: =IF(OR(K5<0,K5>1),"Invalid","Valid") -> Valid | X5: =I5*J5 -> 7742.24 | Y5: =I5*J5-(I5*J5*K5) -> 7355.128
A6: ORD50005 | B6: 45623 | C6: CUST1041 | D6: P008 | E6: Pen Set | F6: Stationery | G6: South | H6: Chennai | I6: 1 | J6: 226.44 | K6: 0.08 | L6: 208.32 | M6: Marketplace | N6: Credit Card | O6: Returned | P6: Sneha | Q6: =PROPER(O6) -> Returned | R6: =PROPER(M6) -> Marketplace | S6: Credit Card | T6: Stationery | U6: =IF(I6<=0,"INVALID","VALID") -> VALID | V6: =IF(I6>100,"REVIEW","NORMAL") -> NORMAL | W6: =IF(OR(K6<0,K6>1),"Invalid","Valid") -> Valid | X6: =I6*J6 -> 226.44 | Y6: =I6*J6-(I6*J6*K6) -> 208.3248
A7: ORD50006 | B7: 45589 | C7: CUST1121 | D7: P014 | E7: Webcam | F7: Electronics | G7: South | H7: Hyderabad | I7: 1 | J7: 2660.88 | K7: 0.08 | L7: 2448.01 | M7: Marketplace | N7: Debit Card | O7: Completed | P7: Priya | Q7: =PROPER(O7) -> Completed | R7: =PROPER(M7) -> Marketplace | S7: Debit Card | T7: Electronics | U7: =IF(I7<=0,"INVALID","VALID") -> VALID | V7: =IF(I7>100,"REVIEW","NORMAL") -> NORMAL | W7: =IF(OR(K7<0,K7>1),"Invalid","Valid") -> Valid | X7: =I7*J7 -> 2660.88 | Y7: =I7*J7-(I7*J7*K7) -> 2448.0096
A8: ORD50007 | B8: 45806 | C8: CUST1217 | D8: P011 | E8: Headphones | F8: Electronics | G8: West | H8: Mumbai | I8: 3 | J8: 3302.54 | K8: 0.03 | L8: 9610.39 | M8: Online | N8: Net Banking | O8: Cancelled | P8: Sneha | Q8: =PROPER(O8) -> Cancelled | R8: =PROPER(M8) -> Online | S8: Net Banking | T8: Electronics | U8: =IF(I8<=0,"INVALID","VALID") -> VALID | V8: =IF(I8>100,"REVIEW","NORMAL") -> NORMAL | W8: =IF(OR(K8<0,K8>1),"Invalid","Valid") -> Valid | X8: =I8*J8 -> 9907.62 | Y8: =I8*J8-(I8*J8*K8) -> 9610.3914
A9: ORD50008 | B9: 46025 | C9: CUST1166 | D9: P013 | E9: Desk Lamp | F9: Furniture | G9: South | H9: Hyderabad | I9: 5 | J9: 1646.72 | K9: 0.05 | L9: 7821.92 | M9: Marketplace | N9: UPI | O9: Cancelled | P9: Anil | Q9: =PROPER(O9) -> Cancelled | R9: =PROPER(M9) -> Marketplace | S9: Upi | T9: Furniture | U9: =IF(I9<=0,"INVALID","VALID") -> VALID | V9: =IF(I9>100,"REVIEW","NORMAL") -> NORMAL | W9: =IF(OR(K9<0,K9>1),"Invalid","Valid") -> Valid | X9: =I9*J9 -> 8233.6 | Y9: =I9*J9-(I9*J9*K9) -> 7821.92
A10: ORD50009 | B10: 46018 | C10: CUST1184 | D10: P012 | E10: Water Bottle | F10: Accessories | G10: West | H10: Ahmedabad | I10: 4 | J10: 888.18 | K10: 0.08 | L10: 3268.5 | M10: Store | N10: Debit Card | O10: Completed | P10: Anil | Q10: =PROPER(O10) -> Completed | R10: =PROPER(M10) -> Store | S10: Debit Card | T10: Accessories | U10: =IF(I10<=0,"INVALID","VALID") -> VALID | V10: =IF(I10>100,"REVIEW","NORMAL") -> NORMAL | W10: =IF(OR(K10<0,K10>1),"Invalid","Valid") -> Valid | X10: =I10*J10 -> 3552.72 | Y10: =I10*J10-(I10*J10*K10) -> 3268.5024
A11: ORD50010 | B11: 45419 | C11: CUST1223 | D11: P004 | E11: Monitor 24-inch | F11: Electronics | G11: North | H11: Lucknow | I11: 3 | J11: 12442.19 | K11: 0.1 | L11: 33593.91 | M11: Online | N11: Net Banking | O11: Completed | P11: Arjun | Q11: =PROPER(O11) -> Completed | R11: =PROPER(M11) -> Online | S11: Net Banking | T11: Electronics | U11: =IF(I11<=0,"INVALID","VALID") -> VALID | V11: =IF(I11>100,"REVIEW","NORMAL") -> NORMAL | W11: =IF(OR(K11<0,K11>1),"Invalid","Valid") -> Valid | X11: =I11*J11 -> 37326.57 | Y11: =I11*J11-(I11*J11*K11) -> 33593.913
A12: ORD50011 | B12: 45807 | C12: CUST1080 | D12: P009 | E12: Backpack | F12: Accessories | G12: North | H12: Jaipur | I12: 3 | J12: 1664.88 | K12: 0.15 | L12: 4245.44 | M12: Store | N12: Cash on Delivery | O12: Completed | P12: Rahul | Q12: =PROPER(O12) -> Completed | R12: =PROPER(M12) -> Store | S12: Cash On Delivery | T12: Accessories | U12: =IF(I12<=0,"INVALID","VALID") -> VALID | V12: =IF(I12>100,"REVIEW","NORMAL") -> NORMAL | W12: =IF(OR(K12<0,K12>1),"Invalid","Valid") -> Valid | X12: =I12*J12 -> 4994.64 | Y12: =I12*J12-(I12*J12*K12) -> 4245.444
A13: ORD50012 | B13: 45664 | C13: CUST1223 | D13: P015 | E13: Phone Stand | F13: Accessories | G13: West | H13: Pune | I13: 1 | J13: 650.53 | K13: 0.03 | L13: 631.01 | M13: Marketplace | N13: Credit Card | O13: Completed | P13: Arjun | Q13: =PROPER(O13) -> Completed | R13: =PROPER(M13) -> Marketplace | S13: Credit Card | T13: Accessories | U13: =IF(I13<=0,"INVALID","VALID") -> VALID | V13: =IF(I13>100,"REVIEW","NORMAL") -> NORMAL | W13: =IF(OR(K13<0,K13>1),"Invalid","Valid") -> Valid | X13: =I13*J13 -> 650.53 | Y13: =I13*J13-(I13*J13*K13) -> 631.0141
A14: ORD50013 | B14: 45407 | C14: CUST1173 | D14: P009 | E14: Backpack | F14: Accessories | G14: East | H14: Bhubaneswar | I14: 4 | J14: 1773.04 | K14: 0.2 | L14: 5673.73 | M14: Marketplace | N14: Credit Card | O14: Completed | P14: Rahul | Q14: =PROPER(O14) -> Completed | R14: =PROPER(M14) -> Marketplace | S14: Credit Card | T14: Accessories | U14: =IF(I14<=0,"INVALID","VALID") -> VALID | V14: =IF(I14>100,"REVIEW","NORMAL") -> NORMAL | W14: =IF(OR(K14<0,K14>1),"Invalid","Valid") -> Valid | X14: =I14*J14 -> 7092.16 | Y14: =I14*J14-(I14*J14*K14) -> 5673.728
... A31: ORD50030 | B31: 45973 | C31: CUST1009 | D31: P006 | E31: Desk | F31: Furniture | G31: South | H31: Hyderabad | I31: 1 | J31: 6901.6 | K31: 0.2 | L31: 5521.28 | M31: Online | N31: Cash on Delivery | O31: Returned | P31: Priya | Q31: =PROPER(O31) -> Returned | R31: =PROPER(M31) -> Online | S31: Cash On Delivery | T31: Furniture | U31: =IF(I31<=0,"INVALID","VALID") -> VALID | V31: =IF(I31>100,"REVIEW","NORMAL") -> NORMAL | W31: =IF(OR(K31<0,K31>1),"Invalid","Valid") -> Valid | X31: =I31*J31 -> 6901.6 | Y31: =I31*J31-(I31*J31*K31) -> 5521.28
A32: ORD50031 | B32: 45973 | D32: P003 | E32: Keyboard | F32: Electronics | G32: South | H32: Visakhapatnam | I32: 3 | J32: 1712.57 | K32: 0.15 | L32: 4367.05 | M32: Online | N32: Cash on Delivery | O32: Cancelled | P32: Rahul | Q32: =PROPER(O32) -> Cancelled | R32: =PROPER(M32) -> Online | S32: Cash On Delivery | T32: Electronics | U32: =IF(I32<=0,"INVALID","VALID") -> VALID | V32: =IF(I32>100,"REVIEW","NORMAL") -> NORMAL | W32: =IF(OR(K32<0,K32>1),"Invalid","Valid") -> Valid | X32: =I32*J32 -> 5137.71 | Y32: =I32*J32-(I32*J32*K32) -> 4367.0535
A33: ORD50032 | B33: 46178 | D33: P008 | E33: Pen Set | F33: Stationery | G33: East | H33: Kolkata | I33: 3 | J33: 202.89 | K33: 0.03 | L33: 590.41 | M33: Online | N33: UPI | O33: Completed | P33: Arjun | Q33: =PROPER(O33) -> Completed | R33: =PROPER(M33) -> Online | S33: Upi | T33: Stationery | U33: =IF(I33<=0,"INVALID","VALID") -> VALID | V33: =IF(I33>100,"REVIEW","NORMAL") -> NORMAL | W33: =IF(OR(K33<0,K33>1),"Invalid","Valid") -> Valid | X33: =I33*J33 -> 608.67 | Y33: =I33*J33-(I33*J33*K33) -> 590.4099
A34: ORD50033 | B34: 46176 | C34: CUST1181 | D34: P002 | E34: Wireless Mouse | F34: Electronics | G34: South | H34: Visakhapatnam | I34: 0 | J34: 1215.57 | K34: 0.2 | L34: 2917.37 | M34: Online | N34: Cash on Delivery | O34: Cancelled | P34: Anil | Q34: =PROPER(O34) -> Cancelled | R34: =PROPER(M34) -> Online | S34: Cash On Delivery | T34: Electronics | U34: =IF(I34<=0,"INVALID","VALID") -> INVALID | V34: =IF(I34>100,"REVIEW","NORMAL") -> NORMAL | W34: =IF(OR(K34<0,K34>1),"Invalid","Valid") -> Valid | X34: =I34*J34 -> 0 | Y34: =I34*J34-(I34*J34*K34) -> 0
A35: ORD50034 | B35: 45944 | C35: CUST1148 | D35: P002 | E35: Wireless Mouse | F35: Electronics | G35: East | H35: Ranchi | I35: 5 | J35: 1127.76 | K35: 0 | L35: 5638.8 | M35: Online | N35: Credit Card | O35: Returned | P35: Rahul | Q35: =PROPER(O35) -> Returned | R35: =PROPER(M35) -> Online | S35: Credit Card | T35: Electronics | U35: =IF(I35<=0,"INVALID","VALID") -> VALID | V35: =IF(I35>100,"REVIEW","NORMAL") -> NORMAL | W35: =IF(OR(K35<0,K35>1),"Invalid","Valid") -> Valid | X35: =I35*J35 -> 5638.8 | Y35: =I35*J35-(I35*J35*K35) -> 5638.8
A36: ORD50035 | B36: 45412 | C36: CUST1249 | D36: P008 | E36: Pen Set | F36: Stationery | G36: East | H36: Ranchi | I36: 4 | J36: 212.48 | K36: 0.05 | L36: 807.42 | M36: Marketplace | N36: Debit Card | O36: Completed | P36: Kiran | Q36: =PROPER(O36) -> Completed | R36: =PROPER(M36) -> Marketplace | S36: Debit Card | T36: Stationery | U36: =IF(I36<=0,"INVALID","VALID") -> VALID | V36: =IF(I36>100,"REVIEW","NORMAL") -> NORMAL | W36: =IF(OR(K36<0,K36>1),"Invalid","Valid") -> Valid | X36: =I36*J36 -> 849.92 | Y36: =I36*J36-(I36*J36*K36) -> 807.424
A37: ORD50036 | B37: 45798 | C37: CUST1195 | D37: P003 | E37: Keyboard | F37: Electronics | G37: East | H37: Bhubaneswar | I37: 5 | J37: 1696.42 | K37: 0 | L37: 8482.1 | M37: Online | N37: Cash on Delivery | O37: Completed | P37: Kiran | Q37: =PROPER(O37) -> Completed | R37: =PROPER(M37) -> Online | S37: Cash On Delivery | T37: Electronics | U37: =IF(I37<=0,"INVALID","VALID") -> VALID | V37: =IF(I37>100,"REVIEW","NORMAL") -> NORMAL | W37: =IF(OR(K37<0,K37>1),"Invalid","Valid") -> Valid | X37: =I37*J37 -> 8482.1 | Y37: =I37*J37-(I37*J37*K37) -> 8482.1
A38: ORD50037 | B38: 45457 | C38: CUST1122 | D38: P014 | E38: Webcam | F38: Electronics | G38: East | H38: Ranchi | I38: 5 | J38: 2927.57 | K38: 0.08 | L38: 13466.82 | M38: Online | N38: Net Banking | O38: Completed | P38: Rahul | Q38: =PROPER(O38) -> Completed | R38: =PROPER(M38) -> Online | S38: Net Banking | T38: Electronics | U38: =IF(I38<=0,"INVALID","VALID") -> VALID | V38: =IF(I38>100,"REVIEW","NORMAL") -> NORMAL | W38: =IF(OR(K38<0,K38>1),"Invalid","Valid") -> Valid | X38: =I38*J38 -> 14637.85 | Y38: =I38*J38-(I38*J38*K38) -> 13466.822
A39: ORD50038 | B39: 46048 | C39: CUST1199 | D39: P004 | E39: Monitor 24-inch | F39: Electronics | G39: West | H39: Ahmedabad | I39: 3 | J39: 12561.54 | K39: 0.03 | L39: 36554.08 | M39: Marketplace | N39: Cash on Delivery | O39: Cancelled | P39: Kiran | Q39: =PROPER(O39) -> Cancelled | R39: =PROPER(M39) -> Marketplace | S39: Cash On Delivery | T39: Electronics | U39: =IF(I39<=0,"INVALID","VALID") -> VALID | V39: =IF(I39>100,"REVIEW","NORMAL") -> NORMAL | W39: =IF(OR(K39<0,K39>1),"Invalid","Valid") -> Valid | X39: =I39*J39 -> 37684.62 | Y39: =I39*J39-(I39*J39*K39) -> 36554.081
A40: ORD50039 | B40: 45556 | C40: CUST1111 | D40: P007 | E40: Notebook Pack | F40: Stationery | G40: North | H40: Chandigarh | I40: 2 | J40: 460.94 | K40: 0.2 | L40: 737.5 | M40: Marketplace | N40: Credit Card | O40: Completed | P40: Kiran | Q40: =PROPER(O40) -> Completed | R40: =PROPER(M40) -> Marketplace | S40: Credit Card | T40: Stationery | U40: =IF(I40<=0,"INVALID","VALID") -> VALID | V40: =IF(I40>100,"REVIEW","NORMAL") -> NORMAL | W40: =IF(OR(K40<0,K40>1),"Invalid","Valid") -> Valid | X40: =I40*J40 -> 921.88 | Y40: =I40*J40-(I40*J40*K40) -> 737.504
A41: ORD50040 | B41: 45518 | C41: CUST1250 | D41: P005 | E41: Office Chair | F41: Furniture | G41: North | H41: Delhi | I41: 5 | J41: 9981.18 | K41: 0.15 | L41: 42420.01 | M41: Marketplace | N41: UPI | O41: Completed | P41: Kiran | Q41: =PROPER(O41) -> Completed | R41: =PROPER(M41) -> Marketplace | S41: Upi | T41: Furniture | U41: =IF(I41<=0,"INVALID","VALID") -> VALID | V41: =IF(I41>100,"REVIEW","NORMAL") -> NORMAL | W41: =IF(OR(K41<0,K41>1),"Invalid","Valid") -> Valid | X41: =I41*J41 -> 49905.9 | Y41: =I41*J41-(I41*J41*K41) -> 42420.015
A42: ORD50041 | B42: 45618 | C42: CUST1081 | D42: P003 | E42: Keyboard | F42: Electronics | G42: North | H42: Chandigarh | I42: 5 | J42: 1697.44 | K42: 0.05 | L42: 8062.84 | M42: Marketplace | N42: Debit Card | O42: Completed | P42: Priya | Q42: =PROPER(O42) -> Completed | R42: =PROPER(M42) -> Marketplace | S42: Debit Card | T42: Electronics | U42: =IF(I42<=0,"INVALID","VALID") -> VALID | V42: =IF(I42>100,"REVIEW","NORMAL") -> NORMAL | W42: =IF(OR(K42<0,K42>1),"Invalid","Valid") -> Valid | X42: =I42*J42 -> 8487.2 | Y42: =I42*J42-(I42*J42*K42) -> 8062.84
A43: ORD50042 | B43: 45551 | C43: CUST1185 | D43: P009 | E43: Backpack | F43: Accessories | G43: North | H43: Delhi | I43: 3 | J43: 1662.09 | K43: 0 | L43: 4986.27 | M43: Online | N43: UPI | O43: Cancelled | P43: Anil | Q43: =PROPER(O43) -> Cancelled | R43: =PROPER(M43) -> Online | S43: Upi | T43: Accessories | U43: =IF(I43<=0,"INVALID","VALID") -> VALID | V43: =IF(I43>100,"REVIEW","NORMAL") -> NORMAL | W43: =IF(OR(K43<0,K43>1),"Invalid","Valid") -> Valid | X43: =I43*J43 -> 4986.27 | Y43: =I43*J43-(I43*J43*K43) -> 4986.27
A44: ORD50043 | B44: 45683 | C44: CUST1103 | D44: P009 | E44: Backpack | F44: Accessories | G44: East | H44: Ranchi | I44: 4 | J44: 1747.58 | K44: 0.15 | L44: 5941.77 | M44: Store | N44: Net Banking | O44: Returned | P44: Meena | Q44: =PROPER(O44) -> Returned | R44: =PROPER(M44) -> Store | S44: Net Banking | T44: Accessories | U44: =IF(I44<=0,"INVALID","VALID") -> VALID | V44: =IF(I44>100,"REVIEW","NORMAL") -> NORMAL | W44: =IF(OR(K44<0,K44>1),"Invalid","Valid") -> Valid | X44: =I44*J44 -> 6990.32 | Y44: =I44*J44-(I44*J44*K44) -> 5941.772
A45: ORD50044 | B45: 46068 | C45: CUST1060 | D45: P009 | E45: Backpack | F45: Accessories | G45: North | H45: Delhi | I45: 3 | J45: 1724.18 | K45: 0.03 | L45: 5017.36 | M45: Store | N45: Debit Card | O45: Returned | P45: Sneha | Q45: =PROPER(O45) -> Returned | R45: =PROPER(M45) -> Store | S45: Debit Card | T45: Accessories | U45: =IF(I45<=0,"INVALID","VALID") -> VALID | V45: =IF(I45>100,"REVIEW","NORMAL") -> NORMAL | W45: =IF(OR(K45<0,K45>1),"Invalid","Valid") -> Valid | X45: =I45*J45 -> 5172.54 | Y45: =I45*J45-(I45*J45*K45) -> 5017.3638
... A54: ORD50053 | B54: 45821 | C54: CUST1036 | D54: P002 | E54: Wireless Mouse | F54: Electronics | G54: East | H54: Kolkata | I54: 5 | J54: 1288.11 | K54: 0.15 | L54: 5474.47 | M54: Marketplace | N54: Debit Card | O54: Completed | P54: Sneha | Q54: =PROPER(O54) -> Completed | R54: =PROPER(M54) -> Marketplace | S54: Debit Card | T54: Electronics | U54: =IF(I54<=0,"INVALID","VALID") -> VALID | V54: =IF(I54>100,"REVIEW","NORMAL") -> NORMAL | W54: =IF(OR(K54<0,K54>1),"Invalid","Valid") -> Valid | X54: =I54*J54 -> 6440.55 | Y54: =I54*J54-(I54*J54*K54) -> 5474.4675
A55: ORD50054 | B55: 46005 | C55: CUST1188 | D55: P015 | E55: Phone Stand | F55: Accessories | G55: West | I55: 5 | J55: 672.38 | K55: 0.2 | L55: 2689.52 | M55: Online | N55: UPI | O55: Completed | P55: Kiran | Q55: =PROPER(O55) -> Completed | R55: =PROPER(M55) -> Online | S55: Upi | T55: Accessories | U55: =IF(I55<=0,"INVALID","VALID") -> VALID | V55: =IF(I55>100,"REVIEW","NORMAL") -> NORMAL | W55: =IF(OR(K55<0,K55>1),"Invalid","Valid") -> Valid | X55: =I55*J55 -> 3361.9 | Y55: =I55*J55-(I55*J55*K55) -> 2689.52
A56: ORD50055 | B56: 45444 | C56: CUST1149 | D56: P003 | E56: Keyboard | F56: Electronics | G56: North | H56: Lucknow | I56: 3 | J56: 1790.2 | L56: 5370.6 | M56: Store | N56: Net Banking | O56: Cancelled | P56: Vikram | Q56: =PROPER(O56) -> Cancelled | R56: =PROPER(M56) -> Store | S56: Net Banking | T56: Electronics | U56: =IF(I56<=0,"INVALID","VALID") -> VALID | V56: =IF(I56>100,"REVIEW","NORMAL") -> NORMAL | W56: =IF(OR(K56<0,K56>1),"Invalid","Valid") -> Valid | X56: =I56*J56 -> 5370.6 | Y56: =I56*J56-(I56*J56*K56) -> 5370.6
A57: ORD50056 | B57: 46020 | C57: CUST1220 | D57: P008 | E57: Pen Set | F57: Stationery | G57: South | H57: Hyderabad | I57: 2 | J57: 235.18 | K57: 0.1 | L57: 423.32 | M57: Marketplace | N57: UPI | O57: Cancelled | P57: Anil | Q57: =PROPER(O57) -> Cancelled | R57: =PROPER(M57) -> Marketplace | S57: Upi | T57: Stationery | U57: =IF(I57<=0,"INVALID","VALID") -> VALID | V57: =IF(I57>100,"REVIEW","NORMAL") -> NORMAL | W57: =IF(OR(K57<0,K57>1),"Invalid","Valid") -> Valid | X57: =I57*J57 -> 470.36 | Y57: =I57*J57-(I57*J57*K57) -> 423.324
A58: ORD50057 | B58: 45737 | C58: CUST1202 | D58: P010 | E58: USB-C Hub | F58: Electronics | G58: East | H58: Patna | I58: 3 | J58: 2260.27 | K58: 0.2 | L58: 5424.65 | M58: Store | N58: Net Banking | O58: Returned | P58: Meena | Q58: =PROPER(O58) -> Returned | R58: =PROPER(M58) -> Store | S58: Net Banking | T58: Electronics | U58: =IF(I58<=0,"INVALID","VALID") -> VALID | V58: =IF(I58>100,"REVIEW","NORMAL") -> NORMAL | W58: =IF(OR(K58<0,K58>1),"Invalid","Valid") -> Valid | X58: =I58*J58 -> 6780.81 | Y58: =I58*J58-(I58*J58*K58) -> 5424.648
A59: ORD50058 | B59: 45987 | D59: P010 | E59: USB-C Hub | F59: Electronics | G59: South | H59: Hyderabad | I59: 4 | J59: 2134.68 | K59: 0.05 | L59: 8111.78 | M59: Marketplace | O59: Completed | P59: Vikram | Q59: =PROPER(O59) -> Completed | R59: =PROPER(M59) -> Marketplace | T59: Electronics | U59: =IF(I59<=0,"INVALID","VALID") -> VALID | V59: =IF(I59>100,"REVIEW","NORMAL") -> NORMAL | W59: =IF(OR(K59<0,K59>1),"Invalid","Valid") -> Valid | X59: =I59*J59 -> 8538.72 | Y59: =I59*J59-(I59*J59*K59) -> 8111.784
A60: ORD50059 | B60: 45798 | C60: CUST1190 | D60: P007 | E60: Notebook Pack | F60: Stationery | G60: East | H60: Ranchi | I60: 2 | J60: 453.82 | K60: 0 | L60: 907.64 | M60: Marketplace | N60: Credit Card | O60: Cancelled | P60: Kiran | Q60: =PROPER(O60) -> Cancelled | R60: =PROPER(M60) -> Marketplace | S60: Credit Card | T60: Stationery | U60: =IF(I60<=0,"INVALID","VALID") -> VALID | V60: =IF(I60>100,"REVIEW","NORMAL") -> NORMAL | W60: =IF(OR(K60<0,K60>1),"Invalid","Valid") -> Valid | X60: =I60*J60 -> 907.64 | Y60: =I60*J60-(I60*J60*K60) -> 907.64
A61: ORD50060 | B61: 45729 | C61: CUST1221 | D61: P003 | E61: Keyboard | F61: Electronics | G61: South | H61: Chennai | I61: -2 | J61: 1862.71 | K61: 0.2 | L61: 5960.67 | M61: Store | N61: UPI | O61: Completed | P61: Meena | Q61: =PROPER(O61) -> Completed | R61: =PROPER(M61) -> Store | S61: Upi | T61: Electronics | U61: =IF(I61<=0,"INVALID","VALID") -> INVALID | V61: =IF(I61>100,"REVIEW","NORMAL") -> NORMAL | W61: =IF(OR(K61<0,K61>1),"Invalid","Valid") -> Valid | X61: =I61*J61 -> -3725.42 | Y61: =I61*J61-(I61*J61*K61) -> -2980.336
A62: ORD50061 | B62: 46092 | C62: CUST1153 | D62: P010 | E62: USB-C Hub | F62: Electronics | G62: North | H62: Lucknow | I62: 1 | J62: 2265.51 | K62: 0.08 | L62: 2084.27 | M62: Online | N62: UPI | O62: Completed | P62: Arjun | Q62: =PROPER(O62) -> Completed | R62: =PROPER(M62) -> Online | S62: Upi | T62: Electronics | U62: =IF(I62<=0,"INVALID","VALID") -> VALID | V62: =IF(I62>100,"REVIEW","NORMAL") -> NORMAL | W62: =IF(OR(K62<0,K62>1),"Invalid","Valid") -> Valid | X62: =I62*J62 -> 2265.51 | Y62: =I62*J62-(I62*J62*K62) -> 2084.2692
A63: ORD50062 | B63: 46044 | C63: CUST1004 | D63: P007 | E63: Notebook Pack | F63: Stationery | G63: South | H63: Visakhapatnam | I63: 5 | J63: 445.85 | K63: 0.08 | L63: 2050.91 | M63: Store | N63: Cash on Delivery | O63: Cancelled | P63: Meena | Q63: =PROPER(O63) -> Cancelled | R63: =PROPER(M63) -> Store | S63: Cash On Delivery | T63: Stationery | U63: =IF(I63<=0,"INVALID","VALID") -> VALID | V63: =IF(I63>100,"REVIEW","NORMAL") -> NORMAL | W63: =IF(OR(K63<0,K63>1),"Invalid","Valid") -> Valid | X63: =I63*J63 -> 2229.25 | Y63: =I63*J63-(I63*J63*K63) -> 2050.91
A64: ORD50063 | B64: 45788 | C64: CUST1229 | D64: P002 | E64: Wireless Mouse | F64: Electronics | G64: South | H64: Chennai | I64: 5 | J64: 1158.51 | K64: 0 | L64: 5792.55 | M64: Marketplace | N64: UPI | O64: Completed | P64: Arjun | Q64: =PROPER(O64) -> Completed | R64: =PROPER(M64) -> Marketplace | S64: Upi | T64: Electronics | U64: =IF(I64<=0,"INVALID","VALID") -> VALID | V64: =IF(I64>100,"REVIEW","NORMAL") -> NORMAL | W64: =IF(OR(K64<0,K64>1),"Invalid","Valid") -> Valid | X64: =I64*J64 -> 5792.55 | Y64: =I64*J64-(I64*J64*K64) -> 5792.55
A65: ORD50064 | B65: 46203 | C65: CUST1177 | D65: P001 | E65: Laptop 15-inch | F65: Electronics | G65: East | H65: Ranchi | I65: 1 | J65: 60740.58 | K65: 0.1 | L65: 54666.52 | M65: Marketplace | N65: UPI | O65: Completed | P65: Priya | Q65: =PROPER(O65) -> Completed | R65: =PROPER(M65) -> Marketplace | S65: Upi | T65: Electronics | U65: =IF(I65<=0,"INVALID","VALID") -> VALID | V65: =IF(I65>100,"REVIEW","NORMAL") -> NORMAL | W65: =IF(OR(K65<0,K65>1),"Invalid","Valid") -> Valid | X65: =I65*J65 -> 60740.58 | Y65: =I65*J65-(I65*J65*K65) -> 54666.522
A66: ORD50065 | B66: 45705 | C66: CUST1052 | D66: P003 | E66: Keyboard | F66: Electronics | G66: West | H66: Pune | I66: 4 | J66: 1918.26 | K66: 0.15 | L66: 6522.08 | M66: Store | N66: Cash on Delivery | O66: Completed | P66: Anil | Q66: =PROPER(O66) -> Completed | R66: =PROPER(M66) -> Store | S66: Cash On Delivery | T66: Electronics | U66: =IF(I66<=0,"INVALID","VALID") -> VALID | V66: =IF(I66>100,"REVIEW","NORMAL") -> NORMAL | W66: =IF(OR(K66<0,K66>1),"Invalid","Valid") -> Valid | X66: =I66*J66 -> 7673.04 | Y66: =I66*J66-(I66*J66*K66) -> 6522.084
A67: ORD50066 | B67: 45296 | C67: CUST1251 | D67: P003 | E67: Keyboard | F67: Electronics | G67: North | H67: Delhi | I67: 5 | J67: 1886.83 | K67: 0.1 | L67: 8490.74 | M67: Online | N67: Cash on Delivery | O67: Completed | P67: Anil | Q67: =PROPER(O67) -> Completed | R67: =PROPER(M67) -> Online | S67: Cash On Delivery | T67: Electronics | U67: =IF(I67<=0,"INVALID","VALID") -> VALID | V67: =IF(I67>100,"REVIEW","NORMAL") -> NORMAL | W67: =IF(OR(K67<0,K67>1),"Invalid","Valid") -> Valid | X67: =I67*J67 -> 9434.15 | Y67: =I67*J67-(I67*J67*K67) -> 8490.735
A68: ORD50067 | B68: 45902 | C68: CUST1201 | D68: P013 | E68: Desk Lamp | F68: Furniture | G68: West | H68: Surat | I68: 5 | J68: 1650.72 | K68: 0 | L68: 8253.6 | M68: Marketplace | N68: Debit Card | O68: Completed | P68: Sneha | Q68: =PROPER(O68) -> Completed | R68: =PROPER(M68) -> Marketplace | S68: Debit Card | T68: Furniture | U68: =IF(I68<=0,"INVALID","VALID") -> VALID | V68: =IF(I68>100,"REVIEW","NORMAL") -> NORMAL | W68: =IF(OR(K68<0,K68>1),"Invalid","Valid") -> Valid | X68: =I68*J68 -> 8253.6 | Y68: =I68*J68-(I68*J68*K68) -> 8253.6
A69: ORD50068 | B69: 45476 | C69: CUST1143 | D69: P002 | E69: Wireless Mouse | F69: Electronics | G69: North | H69: Lucknow | I69: 4 | J69: 1247.08 | K69: 0.08 | L69: 4589.25 | M69: Online | N69: Cash on Delivery | O69: Completed | P69: Priya | Q69: =PROPER(O69) -> Completed | R69: =PROPER(M69) -> Online | S69: Cash On Delivery | T69: Electronics | U69: =IF(I69<=0,"INVALID","VALID") -> VALID | V69: =IF(I69>100,"REVIEW","NORMAL") -> NORMAL | W69: =IF(OR(K69<0,K69>1),"Invalid","Valid") -> Valid | X69: =I69*J69 -> 4988.32 | Y69: =I69*J69-(I69*J69*K69) -> 4589.2544
A70: ORD50069 | B70: 46033 | C70: CUST1071 | D70: P012 | E70: Water Bottle | F70: Accessories | G70: North | I70: 1 | J70: 878.55 | K70: 0 | L70: 878.55 | M70: Marketplace | N70: Net Banking | O70: Completed | P70: Kiran | Q70: =PROPER(O70) -> Completed | R70: =PROPER(M70) -> Marketplace | S70: Net Banking | T70: Accessories | U70: =IF(I70<=0,"INVALID","VALID") -> VALID | V70: =IF(I70>100,"REVIEW","NORMAL") -> NORMAL | W70: =IF(OR(K70<0,K70>1),"Invalid","Valid") -> Valid | X70: =I70*J70 -> 878.55 | Y70: =I70*J70-(I70*J70*K70) -> 878.55
A71: ORD50070 | B71: 45341 | C71: CUST1120 | D71: P002 | E71: Wireless Mouse | F71: Electronics | G71: East | H71: Patna | I71: 1 | J71: 1273.76 | K71: 0 | L71: 1273.76 | M71: Store | N71: UPI | O71: Completed | P71: Anil | Q71: =PROPER(O71) -> Completed | R71: =PROPER(M71) -> Store | S71: Upi | T71: Electronics | U71: =IF(I71<=0,"INVALID","VALID") -> VALID | V71: =IF(I71>100,"REVIEW","NORMAL") -> NORMAL | W71: =IF(OR(K71<0,K71>1),"Invalid","Valid") -> Valid | X71: =I71*J71 -> 1273.76 | Y71: =I71*J71-(I71*J71*K71) -> 1273.76
A72: ORD50071 | B72: 45994 | C72: CUST1120 | D72: P003 | E72: Keyboard | F72: Electronics | G72: South | H72: Visakhapatnam | I72: 5 | J72: 1881.82 | K72: 0.1 | L72: 8468.19 | M72: Store | N72: Cash on Delivery | O72: Completed | Q72: =PROPER(O72) -> Completed | R72: =PROPER(M72) -> Store | S72: Cash On Delivery | T72: Electronics | U72: =IF(I72<=0,"INVALID","VALID") -> VALID | V72: =IF(I72>100,"REVIEW","NORMAL") -> NORMAL | W72: =IF(OR(K72<0,K72>1),"Invalid","Valid") -> Valid | X72: =I72*J72 -> 9409.1 | Y72: =I72*J72-(I72*J72*K72) -> 8468.19
A73: ORD50072 | B73: 45424 | C73: CUST1140 | D73: P004 | E73: Monitor 24-inch | F73: Electronics | G73: West | H73: Ahmedabad | I73: 3 | J73: 12656.03 | K73: 0.05 | L73: 36069.69 | M73: Online | N73: Net Banking | O73: Completed | P73: Vikram | Q73: =PROPER(O73) -> Completed | R73: =PROPER(M73) -> Online | S73: Net Banking | T73: Electronics | U73: =IF(I73<=0,"INVALID","VALID") -> VALID | V73: =IF(I73>100,"REVIEW","NORMAL") -> NORMAL | W73: =IF(OR(K73<0,K73>1),"Invalid","Valid") -> Valid | X73: =I73*J73 -> 37968.09 | Y73: =I73*J73-(I73*J73*K73) -> 36069.686
A74: ORD50073 | B74: 45436 | C74: CUST1106 | D74: P003 | E74: Keyboard | F74: Electronics | G74: South | H74: Hyderabad | I74: 3 | J74: 1792.56 | K74: 0.1 | L74: 4839.91 | M74: Online | N74: Cash on Delivery | O74: Completed | P74: Vikram | Q74: =PROPER(O74) -> Completed | R74: =PROPER(M74) -> Online | S74: Cash On Delivery | T74: Electronics | U74: =IF(I74<=0,"INVALID","VALID") -> VALID | V74: =IF(I74>100,"REVIEW","NORMAL") -> NORMAL | W74: =IF(OR(K74<0,K74>1),"Invalid","Valid") -> Valid | X74: =I74*J74 -> 5377.68 | Y74: =I74*J74-(I74*J74*K74) -> 4839.912
A75: ORD50074 | B75: 45545 | C75: CUST1105 | D75: P002 | E75: Wireless Mouse | F75: Electronics | G75: South | H75: Bengaluru | I75: 4 | J75: 1221.31 | K75: 0.05 | L75: 4640.98 | M75: Marketplace | N75: Debit Card | O75: Completed | P75: Sneha | Q75: =PROPER(O75) -> Completed | R75: =PROPER(M75) -> Marketplace | S75: Debit Card | T75: Electronics | U75: =IF(I75<=0,"INVALID","VALID") -> VALID | V75: =IF(I75>100,"REVIEW","NORMAL") -> NORMAL | W75: =IF(OR(K75<0,K75>1),"Invalid","Valid") -> Valid | X75: =I75*J75 -> 4885.24 | Y75: =I75*J75-(I75*J75*K75) -> 4640.978
A76: ORD50075 | B76: 46058 | C76: CUST1083 | D76: P004 | E76: Monitor 24-inch | F76: Electronics | G76: West | H76: Pune | I76: 3 | J76: 11572.12 | K76: 0.1 | L76: 31244.72 | M76: Store | N76: Debit Card | O76: Completed | P76: Priya | Q76: =PROPER(O76) -> Completed | R76: =PROPER(M76) -> Store | S76: Debit Card | T76: Electronics | U76: =IF(I76<=0,"INVALID","VALID") -> VALID | V76: =IF(I76>100,"REVIEW","NORMAL") -> NORMAL | W76: =IF(OR(K76<0,K76>1),"Invalid","Valid") -> Valid | X76: =I76*J76 -> 34716.36 | Y76: =I76*J76-(I76*J76*K76) -> 31244.724
A77: ORD50076 | B77: 45497 | C77: CUST1143 | D77: P002 | E77: Wireless Mouse | F77: Electronics | G77: East | H77: Patna | I77: 2 | J77: 1238.78 | K77: 0.08 | L77: 2279.36 | M77: Store | N77: Net Banking | O77: Completed | P77: Rahul | Q77: =PROPER(O77) -> Completed | R77: =PROPER(M77) -> Store | S77: Net Banking | T77: Electronics | U77: =IF(I77<=0,"INVALID","VALID") -> VALID | V77: =IF(I77>100,"REVIEW","NORMAL") -> NORMAL | W77: =IF(OR(K77<0,K77>1),"Invalid","Valid") -> Valid | X77: =I77*J77 -> 2477.56 | Y77: =I77*J77-(I77*J77*K77) -> 2279.3552
A78: ORD50077 | B78: 45516 | C78: CUST1113 | D78: P012 | E78: Water Bottle | F78: Accessories | G78: South | H78: Bengaluru | I78: 3 | J78: 867.14 | K78: 0.03 | L78: 2523.38 | M78: Store | N78: Cash on Delivery | O78: Completed | P78: Meena | Q78: =PROPER(O78) -> Completed | R78: =PROPER(M78) -> Store | S78: Cash On Delivery | T78: Accessories | U78: =IF(I78<=0,"INVALID","VALID") -> VALID | V78: =IF(I78>100,"REVIEW","NORMAL") -> NORMAL | W78: =IF(OR(K78<0,K78>1),"Invalid","Valid") -> Valid | X78: =I78*J78 -> 2601.42 | Y78: =I78*J78-(I78*J78*K78) -> 2523.3774
A79: ORD50078 | B79: 45963 | C79: CUST1191 | D79: P009 | E79: Backpack | F79: Accessories | G79: West | I79: 1 | J79: 1801.05 | K79: 0.2 | L79: 1440.84 | M79: Online | N79: Net Banking | O79: Completed | P79: Rahul | Q79: =PROPER(O79) -> Completed | R79: =PROPER(M79) -> Online | S79: Net Banking | T79: Accessories | U79: =IF(I79<=0,"INVALID","VALID") -> VALID | V79: =IF(I79>100,"REVIEW","NORMAL") -> NORMAL | W79: =IF(OR(K79<0,K79>1),"Invalid","Valid") -> Valid | X79: =I79*J79 -> 1801.05 | Y79: =I79*J79-(I79*J79*K79) -> 1440.84
A80: ORD50079 | B80: 45765 | C80: CUST1031 | D80: P013 | E80: Desk Lamp | F80: Furniture | G80: South | H80: Chennai | I80: 3 | J80: 1490.45 | K80: 0 | L80: 4471.35 | M80: Marketplace | N80: Cash on Delivery | O80: Completed | P80: Anil | Q80: =PROPER(O80) -> Completed | R80: =PROPER(M80) -> Marketplace | S80: Cash On Delivery | T80: Furniture | U80: =IF(I80<=0,"INVALID","VALID") -> VALID | V80: =IF(I80>100,"REVIEW","NORMAL") -> NORMAL | W80: =IF(OR(K80<0,K80>1),"Invalid","Valid") -> Valid | X80: =I80*J80 -> 4471.35 | Y80: =I80*J80-(I80*J80*K80) -> 4471.35
A81: ORD50080 | B81: 45547 | C81: CUST1018 | D81: P009 | E81: Backpack | F81: Accessories | G81: South | H81: Bengaluru | I81: 3 | J81: 1746.4 | K81: 0.03 | L81: 5082.02 | M81: Marketplace | N81: UPI | O81: Completed | P81: Meena | Q81: =PROPER(O81) -> Completed | R81: =PROPER(M81) -> Marketplace | S81: Upi | T81: Accessories | U81: =IF(I81<=0,"INVALID","VALID") -> VALID | V81: =IF(I81>100,"REVIEW","NORMAL") -> NORMAL | W81: =IF(OR(K81<0,K81>1),"Invalid","Valid") -> Valid | X81: =I81*J81 -> 5239.2 | Y81: =I81*J81-(I81*J81*K81) -> 5082.024
A82: ORD50081 | B82: 45936 | C82: CUST1040 | D82: P013 | E82: Desk Lamp | F82: Furniture | G82: South | H82: Bengaluru | I82: 2 | J82: 1625.82 | K82: 0.1 | L82: 2926.48 | M82: Online | N82: Debit Card | O82: Completed | P82: Kiran | Q82: =PROPER(O82) -> Completed | R82: =PROPER(M82) -> Online | S82: Debit Card | T82: Furniture | U82: =IF(I82<=0,"INVALID","VALID") -> VALID | V82: =IF(I82>100,"REVIEW","NORMAL") -> NORMAL | W82: =IF(OR(K82<0,K82>1),"Invalid","Valid") -> Valid | X82: =I82*J82 -> 3251.64 | Y82: =I82*J82-(I82*J82*K82) -> 2926.476
A83: ORD50082 | B83: 46166 | D83: P002 | E83: Wireless Mouse | F83: Electronics | G83: West | H83: Ahmedabad | I83: 3 | J83: 1163.7 | K83: 0.15 | L83: 2967.44 | M83: Online | N83: Net Banking | O83: Cancelled | P83: Sneha | Q83: =PROPER(O83) -> Cancelled | R83: =PROPER(M83) -> Online | S83: Net Banking | T83: Electronics | U83: =IF(I83<=0,"INVALID","VALID") -> VALID | V83: =IF(I83>100,"REVIEW","NORMAL") -> NORMAL | W83: =IF(OR(K83<0,K83>1),"Invalid","Valid") -> Valid | X83: =I83*J83 -> 3491.1 | Y83: =I83*J83-(I83*J83*K83) -> 2967.435
A84: ORD50083 | B84: 46136 | C84: CUST1055 | D84: P010 | E84: USB-C Hub | F84: Electronics | G84: South | H84: Visakhapatnam | I84: 1 | J84: 2208.83 | K84: 0.1 | L84: 1987.95 | M84: Online | N84: Net Banking | O84: Completed | P84: Sneha | Q84: =PROPER(O84) -> Completed | R84: =PROPER(M84) -> Online | S84: Net Banking | T84: Electronics | U84: =IF(I84<=0,"INVALID","VALID") -> VALID | V84: =IF(I84>100,"REVIEW","NORMAL") -> NORMAL | W84: =IF(OR(K84<0,K84>1),"Invalid","Valid") -> Valid | X84: =I84*J84 -> 2208.83 | Y84: =I84*J84-(I84*J84*K84) -> 1987.947
A85: ORD50084 | B85: 46054 | C85: CUST1209 | D85: P014 | E85: Webcam | F85: Electronics | G85: West | H85: Surat | I85: 5 | J85: 2951.9 | K85: 0.08 | L85: 13578.74 | M85: Store | N85: UPI | O85: Completed | P85: Sneha | Q85: =PROPER(O85) -> Completed | R85: =PROPER(M85) -> Store | S85: Upi | T85: Electronics | U85: =IF(I85<=0,"INVALID","VALID") -> VALID | V85: =IF(I85>100,"REVIEW","NORMAL") -> NORMAL | W85: =IF(OR(K85<0,K85>1),"Invalid","Valid") -> Valid | X85: =I85*J85 -> 14759.5 | Y85: =I85*J85-(I85*J85*K85) -> 13578.74
A86: ORD50085 | B86: 46060 | C86: CUST1197 | D86: P006 | E86: Desk | F86: Furniture | G86: South | H86: Visakhapatnam | I86: 1 | J86: 7123.71 | K86: 0.15 | L86: 6055.15 | M86: Store | O86: Completed | P86: Rahul | Q86: =PROPER(O86) -> Completed | R86: =PROPER(M86) -> Store | T86: Furniture | U86: =IF(I86<=0,"INVALID","VALID") -> VALID | V86: =IF(I86>100,"REVIEW","NORMAL") -> NORMAL | W86: =IF(OR(K86<0,K86>1),"Invalid","Valid") -> Valid | X86: =I86*J86 -> 7123.71 | Y86: =I86*J86-(I86*J86*K86) -> 6055.1535
A87: ORD50086 | B87: 45457 | C87: CUST1051 | D87: P004 | E87: Monitor 24-inch | F87: Electronics | G87: West | H87: Pune | I87: 5 | J87: 11965.7 | K87: 0 | L87: 59828.5 | M87: Online | O87: Returned | P87: Kiran | Q87: =PROPER(O87) -> Returned | R87: =PROPER(M87) -> Online | T87: Electronics | U87: =IF(I87<=0,"INVALID","VALID") -> VALID | V87: =IF(I87>100,"REVIEW","NORMAL") -> NORMAL | W87: =IF(OR(K87<0,K87>1),"Invalid","Valid") -> Valid | X87: =I87*J87 -> 59828.5 | Y87: =I87*J87-(I87*J87*K87) -> 59828.5
A88: ORD50087 | B88: 45951 | C88: CUST1064 | D88: P008 | E88: Pen Set | F88: Stationery | G88: North | H88: Chandigarh | I88: 1 | J88: 232.09 | K88: 0.03 | L88: 225.13 | M88: Store | N88: Debit Card | O88: Completed | P88: Sneha | Q88: =PROPER(O88) -> Completed | R88: =PROPER(M88) -> Store | S88: Debit Card | T88: Stationery | U88: =IF(I88<=0,"INVALID","VALID") -> VALID | V88: =IF(I88>100,"REVIEW","NORMAL") -> NORMAL | W88: =IF(OR(K88<0,K88>1),"Invalid","Valid") -> Valid | X88: =I88*J88 -> 232.09 | Y88: =I88*J88-(I88*J88*K88) -> 225.1273
A89: ORD50088 | B89: 45903 | C89: CUST1194 | D89: P012 | E89: Water Bottle | F89: Accessories | G89: West | H89: Ahmedabad | I89: 4 | J89: 831.86 | K89: 0 | L89: 3327.44 | M89: Marketplace | N89: Credit Card | O89: Returned | P89: Meena | Q89: =PROPER(O89) -> Returned | R89: =PROPER(M89) -> Marketplace | S89: Credit Card | T89: Accessories | U89: =IF(I89<=0,"INVALID","VALID") -> VALID | V89: =IF(I89>100,"REVIEW","NORMAL") -> NORMAL | W89: =IF(OR(K89<0,K89>1),"Invalid","Valid") -> Valid | X89: =I89*J89 -> 3327.44 | Y89: =I89*J89-(I89*J89*K89) -> 3327.44
A90: ORD50089 | B90: 45593 | C90: CUST1222 | D90: P008 | E90: Pen Set | F90: Stationery | G90: east | H90: Bhubaneswar | I90: 4 | J90: 220.17 | K90: 0.1 | L90: 792.61 | M90: Marketplace | N90: Credit Card | O90: Completed | P90: Anil | Q90: =PROPER(O90) -> Completed | R90: =PROPER(M90) -> Marketplace | S90: Credit Card | T90: Stationery | U90: =IF(I90<=0,"INVALID","VALID") -> VALID | V90: =IF(I90>100,"REVIEW","NORMAL") -> NORMAL | W90: =IF(OR(K90<0,K90>1),"Invalid","Valid") -> Valid | X90: =I90*J90 -> 880.68 | Y90: =I90*J90-(I90*J90*K90) -> 792.612
A91: ORD50090 | B91: 46067 | D91: P006 | E91: Desk | F91: Furniture | G91: South | H91: Hyderabad | I91: 3 | J91: 7236.19 | K91: 0.08 | L91: 19971.88 | M91: Online | N91: Credit Card | O91: Returned | P91: Vikram | Q91: =PROPER(O91) -> Returned | R91: =PROPER(M91) -> Online | S91: Credit Card | T91: Furniture | U91: =IF(I91<=0,"INVALID","VALID") -> VALID | V91: =IF(I91>100,"REVIEW","NORMAL") -> NORMAL | W91: =IF(OR(K91<0,K91>1),"Invalid","Valid") -> Valid | X91: =I91*J91 -> 21708.57 | Y91: =I91*J91-(I91*J91*K91) -> 19971.884
A92: ORD50091 | B92: 45865 | C92: CUST1089 | D92: P010 | E92: USB-C Hub | F92: Electronics | G92: South | H92: Visakhapatnam | I92: 1 | J92: 2091.44 | K92: 0 | L92: 2091.44 | M92: Online | N92: Net Banking | O92: Returned | P92: Arjun | Q92: =PROPER(O92) -> Returned | R92: =PROPER(M92) -> Online | S92: Net Banking | T92: Electronics | U92: =IF(I92<=0,"INVALID","VALID") -> VALID | V92: =IF(I92>100,"REVIEW","NORMAL") -> NORMAL | W92: =IF(OR(K92<0,K92>1),"Invalid","Valid") -> Valid | X92: =I92*J92 -> 2091.44 | Y92: =I92*J92-(I92*J92*K92) -> 2091.44
A93: ORD50092 | B93: 45700 | C93: CUST1109 | D93: P007 | E93: Notebook Pack | F93: Stationery | G93: south | H93: Visakhapatnam | I93: 1 | J93: 414.53 | K93: 0.1 | L93: 373.08 | M93: Online | N93: Net Banking | O93: Completed | P93: Arjun | Q93: =PROPER(O93) -> Completed | R93: =PROPER(M93) -> Online | S93: Net Banking | T93: Stationery | U93: =IF(I93<=0,"INVALID","VALID") -> VALID | V93: =IF(I93>100,"REVIEW","NORMAL") -> NORMAL | W93: =IF(OR(K93<0,K93>1),"Invalid","Valid") -> Valid | X93: =I93*J93 -> 414.53 | Y93: =I93*J93-(I93*J93*K93) -> 373.077
A94: ORD50093 | B94: 45942 | C94: CUST1125 | D94: P015 | E94: Phone Stand | F94: Accessories | G94: West | H94: Ahmedabad | I94: 4 | J94: 729.28 | K94: 0.2 | L94: 2333.7 | M94: Marketplace | N94: Debit Card | O94: Cancelled | P94: Rahul | Q94: =PROPER(O94) -> Cancelled | R94: =PROPER(M94) -> Marketplace | S94: Debit Card | T94: Accessories | U94: =IF(I94<=0,"INVALID","VALID") -> VALID | V94: =IF(I94>100,"REVIEW","NORMAL") -> NORMAL | W94: =IF(OR(K94<0,K94>1),"Invalid","Valid") -> Valid | X94: =I94*J94 -> 2917.12 | Y94: =I94*J94-(I94*J94*K94) -> 2333.696
A95: ORD50094 | B95: 46170 | C95: CUST1132 | D95: P010 | E95: USB-C Hub | F95: Electronics | G95: West | H95: Ahmedabad | I95: 3 | J95: 2064.16 | K95: 0.2 | L95: 4953.98 | M95: Marketplace | N95: Debit Card | O95: Completed | P95: Kiran | Q95: =PROPER(O95) -> Completed | R95: =PROPER(M95) -> Marketplace | S95: Debit Card | T95: Electronics | U95: =IF(I95<=0,"INVALID","VALID") -> VALID | V95: =IF(I95>100,"REVIEW","NORMAL") -> NORMAL | W95: =IF(OR(K95<0,K95>1),"Invalid","Valid") -> Valid | X95: =I95*J95 -> 6192.48 | Y95: =I95*J95-(I95*J95*K95) -> 4953.984
A96: ORD50095 | B96: 46168 | C96: CUST1256 | D96: P010 | E96: USB-C Hub | F96: Electronics | G96: South | H96: Chennai | I96: 5 | J96: 2125.46 | K96: 0 | L96: 10627.3 | M96: Marketplace | N96: Cash on Delivery | O96: Cancelled | P96: Arjun | Q96: =PROPER(O96) -> Cancelled | R96: =PROPER(M96) -> Marketplace | S96: Cash On Delivery | T96: Electronics | U96: =IF(I96<=0,"INVALID","VALID") -> VALID | V96: =IF(I96>100,"REVIEW","NORMAL") -> NORMAL | W96: =IF(OR(K96<0,K96>1),"Invalid","Valid") -> Valid | X96: =I96*J96 -> 10627.3 | Y96: =I96*J96-(I96*J96*K96) -> 10627.3
A97: ORD50096 | B97: 45608 | C97: CUST1251 | D97: P001 | E97: Laptop 15-inch | F97: Electronics | G97: North | H97: Jaipur | I97: 2 | J97: 67884.37 | K97: 0 | L97: 135768.74 | M97: Marketplace | N97: Cash on Delivery | O97: Returned | P97: Sneha | Q97: =PROPER(O97) -> Returned | R97: =PROPER(M97) -> Marketplace | S97: Cash On Delivery | T97: Electronics | U97: =IF(I97<=0,"INVALID","VALID") -> VALID | V97: =IF(I97>100,"REVIEW","NORMAL") -> NORMAL | W97: =IF(OR(K97<0,K97>1),"Invalid","Valid") -> Valid | X97: =I97*J97 -> 135768.74 | Y97: =I97*J97-(I97*J97*K97) -> 135768.74
A98: ORD50097 | B98: 45588 | C98: CUST1207 | D98: P015 | E98: Phone Stand | F98: Accessories | G98: North | H98: Delhi | I98: 3 | J98: 653.5 | K98: 0 | L98: 1960.5 | M98: Store | N98: Debit Card | O98: Cancelled | P98: Rahul | Q98: =PROPER(O98) -> Cancelled | R98: =PROPER(M98) -> Store | S98: Debit Card | T98: Accessories | U98: =IF(I98<=0,"INVALID","VALID") -> VALID | V98: =IF(I98>100,"REVIEW","NORMAL") -> NORMAL | W98: =IF(OR(K98<0,K98>1),"Invalid","Valid") -> Valid | X98: =I98*J98 -> 1960.5 | Y98: =I98*J98-(I98*J98*K98) -> 1960.5
A99: ORD50098 | B99: 46135 | C99: CUST1248 | D99: P007 | E99: Notebook Pack | F99: Stationery | G99: West | H99: Mumbai | I99: 2 | J99: 440.83 | K99: 0 | L99: 881.66 | M99: Store | N99: UPI | O99: Returned | P99: Arjun | Q99: =PROPER(O99) -> Returned | R99: =PROPER(M99) -> Store | S99: Upi | T99: Stationery | U99: =IF(I99<=0,"INVALID","VALID") -> VALID | V99: =IF(I99>100,"REVIEW","NORMAL") -> NORMAL | W99: =IF(OR(K99<0,K99>1),"Invalid","Valid") -> Valid | X99: =I99*J99 -> 881.66 | Y99: =I99*J99-(I99*J99*K99) -> 881.66
A100: ORD50099 | B100: 45987 | C100: CUST1226 | D100: P011 | E100: Headphones | F100: Electronics | G100: East | H100: Bhubaneswar | I100: 4 | J100: 3322.59 | K100: 0 | L100: 13290.36 | M100: Marketplace | N100: Credit Card | O100: Completed | P100: Vikram | Q100: =PROPER(O100) -> Completed | R100: =PROPER(M100) -> Marketplace | S100: Credit Card | T100: Electronics | U100: =IF(I100<=0,"INVALID","VALID") -> VALID | V100: =IF(I100>100,"REVIEW","NORMAL") -> NORMAL | W100: =IF(OR(K100<0,K100>1),"Invalid","Valid") -> Valid | X100: =I100*J100 -> 13290.36 | Y100: =I100*J100-(I100*J100*K100) -> 13290.36
A101: ORD50100 | B101: 45505 | C101: CUST1248 | D101: P002 | E101: Wireless Mouse | F101: Electronics | G101: East | H101: Patna | I101: 2 | J101: 1104.86 | K101: 0.2 | L101: 1767.78 | M101: Online | N101: Net Banking | O101: Completed | P101: Anil | Q101: =PROPER(O101) -> Completed | R101: =PROPER(M101) -> Online | S101: Net Banking | T101: Electronics | U101: =IF(I101<=0,"INVALID","VALID") -> VALID | V101: =IF(I101>100,"REVIEW","NORMAL") -> NORMAL | W101: =IF(OR(K101<0,K101>1),"Invalid","Valid") -> Valid | X101: =I101*J101 -> 2209.72 | Y101: =I101*J101-(I101*J101*K101) -> 1767.776
A102: ORD50101 | B102: 45984 | C102: CUST1175 | D102: P007 | E102: Notebook Pack | F102: Stationery | G102: East | H102: Bhubaneswar | I102: 5 | J102: 431.11 | K102: 0.1 | L102: 1940 | M102: Marketplace | N102: Debit Card | O102: Completed | P102: Meena | Q102: =PROPER(O102) -> Completed | R102: =PROPER(M102) -> Marketplace | S102: Debit Card | T102: Stationery | U102: =IF(I102<=0,"INVALID","VALID") -> VALID | V102: =IF(I102>100,"REVIEW","NORMAL") -> NORMAL | W102: =IF(OR(K102<0,K102>1),"Invalid","Valid") -> Valid | X102: =I102*J102 -> 2155.55 | Y102: =I102*J102-(I102*J102*K102) -> 1939.995
A103: ORD50102 | B103: 46070 | C103: CUST1030 | D103: P014 | E103: Webcam | F103: Electronics | G103: South | H103: Visakhapatnam | I103: 4 | J103: 2753.83 | K103: 0.1 | L103: 9913.79 | M103: Store | N103: Cash on Delivery | O103: Returned | P103: Priya | Q103: =PROPER(O103) -> Returned | R103: =PROPER(M103) -> Store | S103: Cash On Delivery | T103: Electronics | U103: =IF(I103<=0,"INVALID","VALID") -> VALID | V103: =IF(I103>100,"REVIEW","NORMAL") -> NORMAL | W103: =IF(OR(K103<0,K103>1),"Invalid","Valid") -> Valid | X103: =I103*J103 -> 11015.32 | Y103: =I103*J103-(I103*J103*K103) -> 9913.788
... A113: ORD50112 | B113: 45686 | C113: CUST1077 | D113: P003 | E113: Keyboard | F113: Electronics | G113: North | H113: Delhi | I113: 5 | J113: 1685.66 | K113: 0.2 | L113: 6742.64 | M113: Online | N113: Credit Card | O113: Completed | P113: Anil | Q113: =PROPER(O113) -> Completed | R113: =PROPER(M113) -> Online | S113: Credit Card | T113: Electronics | U113: =IF(I113<=0,"INVALID","VALID") -> VALID | V113: =IF(I113>100,"REVIEW","NORMAL") -> NORMAL | W113: =IF(OR(K113<0,K113>1),"Invalid","Valid") -> Valid | X113: =I113*J113 -> 8428.3 | Y113: =I113*J113-(I113*J113*K113) -> 6742.64
A114: ORD50113 | B114: 46189 | C114: CUST1082 | D114: P007 | E114: Notebook Pack | F114: Stationery | G114: South | H114: Chennai | J114: 417.67 | K114: 0.15 | L114: 1065.06 | M114: Online | N114: Net Banking | O114: Completed | P114: Meena | Q114: =PROPER(O114) -> Completed | R114: =PROPER(M114) -> Online | S114: Net Banking | T114: Stationery | U114: =IF(I114<=0,"INVALID","VALID") -> INVALID | V114: =IF(I114>100,"REVIEW","NORMAL") -> NORMAL | W114: =IF(OR(K114<0,K114>1),"Invalid","Valid") -> Valid | X114: =I114*J114 -> 0 | Y114: =I114*J114-(I114*J114*K114) -> 0
A115: ORD50114 | B115: 45347 | C115: CUST1128 | D115: P014 | E115: Webcam | F115: Electronics | G115: East | H115: Bhubaneswar | I115: 3 | J115: 2711.33 | K115: 0.03 | L115: 7889.97 | M115: Online | N115: Debit Card | O115: Completed | P115: Anil | Q115: =PROPER(O115) -> Completed | R115: =PROPER(M115) -> Online | S115: Debit Card | T115: Electronics | U115: =IF(I115<=0,"INVALID","VALID") -> VALID | V115: =IF(I115>100,"REVIEW","NORMAL") -> NORMAL | W115: =IF(OR(K115<0,K115>1),"Invalid","Valid") -> Valid | X115: =I115*J115 -> 8133.99 | Y115: =I115*J115-(I115*J115*K115) -> 7889.9703
A116: ORD50115 | B116: 45556 | C116: CUST1001 | D116: P002 | E116: Wireless Mouse | F116: Electronics | G116: South | H116: Visakhapatnam | I116: 5 | J116: 1201.57 | K116: 0.03 | L116: 5827.61 | M116: Store | N116: UPI | O116: Completed | P116: Sneha | Q116: =PROPER(O116) -> Completed | R116: =PROPER(M116) -> Store | S116: Upi | T116: Electronics | U116: =IF(I116<=0,"INVALID","VALID") -> VALID | V116: =IF(I116>100,"REVIEW","NORMAL") -> NORMAL | W116: =IF(OR(K116<0,K116>1),"Invalid","Valid") -> Valid | X116: =I116*J116 -> 6007.85 | Y116: =I116*J116-(I116*J116*K116) -> 5827.6145
A117: ORD50116 | B117: 45685 | D117: P009 | E117: Backpack | F117: Accessories | G117: West | H117: Pune | I117: 3 | J117: 1730.98 | K117: 0.15 | L117: 4414 | M117: Store | N117: Credit Card | O117: Returned | P117: Sneha | Q117: =PROPER(O117) -> Returned | R117: =PROPER(M117) -> Store | S117: Credit Card | T117: Accessories | U117: =IF(I117<=0,"INVALID","VALID") -> VALID | V117: =IF(I117>100,"REVIEW","NORMAL") -> NORMAL | W117: =IF(OR(K117<0,K117>1),"Invalid","Valid") -> Valid | X117: =I117*J117 -> 5192.94 | Y117: =I117*J117-(I117*J117*K117) -> 4413.999
A118: ORD50117 | B118: 46079 | C118: CUST1086 | D118: P011 | E118: Headphones | F118: Electronics | G118: South | H118: Visakhapatnam | I118: 2 | J118: 3420.36 | K118: 0.15 | L118: 5814.61 | M118: Online | N118: Debit Card | O118: Completed | P118: Meena | Q118: =PROPER(O118) -> Completed | R118: =PROPER(M118) -> Online | S118: Debit Card | T118: Electronics | U118: =IF(I118<=0,"INVALID","VALID") -> VALID | V118: =IF(I118>100,"REVIEW","NORMAL") -> NORMAL | W118: =IF(OR(K118<0,K118>1),"Invalid","Valid") -> Valid | X118: =I118*J118 -> 6840.72 | Y118: =I118*J118-(I118*J118*K118) -> 5814.612
A119: ORD50118 | B119: 45940 | C119: CUST1006 | D119: P003 | E119: Keyboard | F119: Electronics | G119: North | H119: Chandigarh | I119: 4 | J119: 1695.8 | K119: 0 | L119: 6783.2 | M119: Online | N119: UPI | O119: Returned | P119: Priya | Q119: =PROPER(O119) -> Returned | R119: =PROPER(M119) -> Online | S119: Upi | T119: Electronics | U119: =IF(I119<=0,"INVALID","VALID") -> VALID | V119: =IF(I119>100,"REVIEW","NORMAL") -> NORMAL | W119: =IF(OR(K119<0,K119>1),"Invalid","Valid") -> Valid | X119: =I119*J119 -> 6783.2 | Y119: =I119*J119-(I119*J119*K119) -> 6783.2
A120: ORD50119 | B120: 46036 | C120: CUST1162 | D120: P001 | E120: Laptop 15-inch | F120: Electronics | G120: North | H120: Delhi | I120: 1 | J120: 62313.04 | K120: 0.1 | L120: 56081.74 | M120: Store | N120: Credit Card | O120: Completed | P120: Arjun | Q120: =PROPER(O120) -> Completed | R120: =PROPER(M120) -> Store | S120: Credit Card | T120: Electronics | U120: =IF(I120<=0,"INVALID","VALID") -> VALID | V120: =IF(I120>100,"REVIEW","NORMAL") -> NORMAL | W120: =IF(OR(K120<0,K120>1),"Invalid","Valid") -> Valid | X120: =I120*J120 -> 62313.04 | Y120: =I120*J120-(I120*J120*K120) -> 56081.736
A121: ORD50120 | B121: 46066 | C121: CUST1120 | D121: P008 | E121: Pen Set | F121: Stationery | G121: North | H121: Delhi | I121: 2 | J121: 224.19 | K121: 0.15 | L121: 381.12 | M121: Marketplace | N121: Net Banking | O121: Returned | P121: Meena | Q121: =PROPER(O121) -> Returned | R121: =PROPER(M121) -> Marketplace | S121: Net Banking | T121: Stationery | U121: =IF(I121<=0,"INVALID","VALID") -> VALID | V121: =IF(I121>100,"REVIEW","NORMAL") -> NORMAL | W121: =IF(OR(K121<0,K121>1),"Invalid","Valid") -> Valid | X121: =I121*J121 -> 448.38 | Y121: =I121*J121-(I121*J121*K121) -> 381.123
A122: ORD50121 | B122: 45557 | C122: CUST1119 | D122: P004 | E122: Monitor 24-inch | F122: Electronics | G122: North | H122: Chandigarh | I122: 5 | J122: 12706.85 | K122: 0.08 | L122: 58451.51 | M122: Marketplace | N122: UPI | O122: Completed | P122: Arjun | Q122: =PROPER(O122) -> Completed | R122: =PROPER(M122) -> Marketplace | S122: Upi | T122: Electronics | U122: =IF(I122<=0,"INVALID","VALID") -> VALID | V122: =IF(I122>100,"REVIEW","NORMAL") -> NORMAL | W122: =IF(OR(K122<0,K122>1),"Invalid","Valid") -> Valid | X122: =I122*J122 -> 63534.25 | Y122: =I122*J122-(I122*J122*K122) -> 58451.51
A123: ORD50122 | B123: 46033 | C123: CUST1078 | D123: P003 | E123: Keyboard | F123: Electronics | G123: South | H123: Hyderabad | I123: 3 | J123: 1829.01 | K123: 0.15 | L123: 4663.98 | M123: Store | N123: Debit Card | O123: Completed | P123: Rahul | Q123: =PROPER(O123) -> Completed | R123: =PROPER(M123) -> Store | S123: Debit Card | T123: Electronics | U123: =IF(I123<=0,"INVALID","VALID") -> VALID | V123: =IF(I123>100,"REVIEW","NORMAL") -> NORMAL | W123: =IF(OR(K123<0,K123>1),"Invalid","Valid") -> Valid | X123: =I123*J123 -> 5487.03 | Y123: =I123*J123-(I123*J123*K123) -> 4663.9755
A124: ORD50123 | B124: 46042 | C124: CUST1091 | D124: P002 | E124: Wireless Mouse | F124: Electronics | G124: West | H124: Ahmedabad | I124: 1 | J124: 1107.65 | K124: 0.15 | L124: 941.5 | M124: Online | N124: Net Banking | O124: Cancelled | P124: Meena | Q124: =PROPER(O124) -> Cancelled | R124: =PROPER(M124) -> Online | S124: Net Banking | T124: Electronics | U124: =IF(I124<=0,"INVALID","VALID") -> VALID | V124: =IF(I124>100,"REVIEW","NORMAL") -> NORMAL | W124: =IF(OR(K124<0,K124>1),"Invalid","Valid") -> Valid | X124: =I124*J124 -> 1107.65 | Y124: =I124*J124-(I124*J124*K124) -> 941.5025
A125: ORD50124 | B125: 45937 | C125: CUST1039 | D125: P005 | E125: Office Chair | F125: Furniture | G125: East | H125: Patna | I125: 5 | J125: 10092.83 | K125: 0.05 | L125: 47940.94 | M125: Online | N125: UPI | O125: Cancelled | P125: Priya | Q125: =PROPER(O125) -> Cancelled | R125: =PROPER(M125) -> Online | S125: Upi | T125: Furniture | U125: =IF(I125<=0,"INVALID","VALID") -> VALID | V125: =IF(I125>100,"REVIEW","NORMAL") -> NORMAL | W125: =IF(OR(K125<0,K125>1),"Invalid","Valid") -> Valid | X125: =I125*J125 -> 50464.15 | Y125: =I125*J125-(I125*J125*K125) -> 47940.943
A126: ORD50125 | B126: 45903 | C126: CUST1132 | D126: P011 | E126: Headphones | F126: Electronics | G126: North | H126: Jaipur | I126: 1 | J126: 3451.79 | K126: 0.15 | L126: 2934.02 | M126: Online | N126: Cash on Delivery | O126: Completed | P126: Kiran | Q126: =PROPER(O126) -> Completed | R126: =PROPER(M126) -> Online | S126: Cash On Delivery | T126: Electronics | U126: =IF(I126<=0,"INVALID","VALID") -> VALID | V126: =IF(I126>100,"REVIEW","NORMAL") -> NORMAL | W126: =IF(OR(K126<0,K126>1),"Invalid","Valid") -> Valid | X126: =I126*J126 -> 3451.79 | Y126: =I126*J126-(I126*J126*K126) -> 2934.0215
A127: ORD50126 | B127: 46197 | C127: CUST1024 | D127: P009 | E127: Backpack | F127: Accessories | G127: East | H127: Ranchi | I127: 2 | J127: 1914.42 | K127: 0 | L127: 3828.84 | M127: Store | N127: Debit Card | O127: Completed | P127: Kiran | Q127: =PROPER(O127) -> Completed | R127: =PROPER(M127) -> Store | S127: Debit Card | T127: Accessories | U127: =IF(I127<=0,"INVALID","VALID") -> VALID | V127: =IF(I127>100,"REVIEW","NORMAL") -> NORMAL | W127: =IF(OR(K127<0,K127>1),"Invalid","Valid") -> Valid | X127: =I127*J127 -> 3828.84 | Y127: =I127*J127-(I127*J127*K127) -> 3828.84
A128: ORD50127 | B128: 45458 | C128: CUST1155 | D128: P005 | E128: Office Chair | F128: Furniture | G128: East | H128: Bhubaneswar | I128: 1 | J128: 9188.03 | K128: 0.08 | L128: 8452.99 | M128: Store | N128: Cash on Delivery | O128: Returned | P128: Priya | Q128: =PROPER(O128) -> Returned | R128: =PROPER(M128) -> Store | S128: Cash On Delivery | T128: Furniture | U128: =IF(I128<=0,"INVALID","VALID") -> VALID | V128: =IF(I128>100,"REVIEW","NORMAL") -> NORMAL | W128: =IF(OR(K128<0,K128>1),"Invalid","Valid") -> Valid | X128: =I128*J128 -> 9188.03 | Y128: =I128*J128-(I128*J128*K128) -> 8452.9876
A129: ORD50128 | B129: 45308 | C129: CUST1219 | D129: P001 | E129: Laptop 15-inch | F129: Electronics | G129: East | H129: Bhubaneswar | I129: 1 | J129: 68888.44 | K129: 0.03 | L129: 66821.79 | M129: Store | N129: Net Banking | O129: Completed | P129: Kiran | Q129: =PROPER(O129) -> Completed | R129: =PROPER(M129) -> Store | S129: Net Banking | T129: Electronics | U129: =IF(I129<=0,"INVALID","VALID") -> VALID | V129: =IF(I129>100,"REVIEW","NORMAL") -> NORMAL | W129: =IF(OR(K129<0,K129>1),"Invalid","Valid") -> Valid | X129: =I129*J129 -> 68888.44 | Y129: =I129*J129-(I129*J129*K129) -> 66821.787
... A184: ORD50183 | B184: 45599 | C184: CUST1215 | D184: P003 | E184: Keyboard | F184: Electronics | G184: North | H184: Lucknow | I184: 1 | J184: 1770.77 | K184: 0 | L184: 1770.77 | M184: Marketplace | N184: Cash on Delivery | O184: Completed | P184: Vikram | Q184: =PROPER(O184) -> Completed | R184: =PROPER(M184) -> Marketplace | S184: Cash On Delivery | T184: Electronics | U184: =IF(I184<=0,"INVALID","VALID") -> VALID | V184: =IF(I184>100,"REVIEW","NORMAL") -> NORMAL | W184: =IF(OR(K184<0,K184>1),"Invalid","Valid") -> Valid | X184: =I184*J184 -> 1770.77 | Y184: =I184*J184-(I184*J184*K184) -> 1770.77
A185: ORD50184 | B185: 45888 | C185: CUST1248 | D185: P003 | E185: Keyboard | F185: Electronics | G185: South | I185: 5 | J185: 1908.02 | K185: 0.05 | L185: 9063.09 | M185: Marketplace | N185: Cash on Delivery | O185: Completed | P185: Priya | Q185: =PROPER(O185) -> Completed | R185: =PROPER(M185) -> Marketplace | S185: Cash On Delivery | T185: Electronics | U185: =IF(I185<=0,"INVALID","VALID") -> VALID | V185: =IF(I185>100,"REVIEW","NORMAL") -> NORMAL | W185: =IF(OR(K185<0,K185>1),"Invalid","Valid") -> Valid | X185: =I185*J185 -> 9540.1 | Y185: =I185*J185-(I185*J185*K185) -> 9063.095
A186: ORD50185 | B186: 45854 | C186: CUST1076 | D186: P004 | E186: Monitor 24-inch | F186: Electronics | G186: South | H186: Hyderabad | I186: 4 | J186: 12969.45 | K186: 0.2 | L186: 41502.24 | M186: Store | N186: Net Banking | O186: Completed | P186: Sneha | Q186: =PROPER(O186) -> Completed | R186: =PROPER(M186) -> Store | S186: Net Banking | T186: Electronics | U186: =IF(I186<=0,"INVALID","VALID") -> VALID | V186: =IF(I186>100,"REVIEW","NORMAL") -> NORMAL | W186: =IF(OR(K186<0,K186>1),"Invalid","Valid") -> Valid | X186: =I186*J186 -> 51877.8 | Y186: =I186*J186-(I186*J186*K186) -> 41502.24
A187: ORD50186 | B187: 46047 | C187: CUST1243 | D187: P006 | E187: Desk | F187: Furniture | G187: East | H187: Patna | I187: 3 | J187: 6680.98 | K187: 0 | L187: 20042.94 | M187: Store | N187: Debit Card | O187: Completed | P187: Rahul | Q187: =PROPER(O187) -> Completed | R187: =PROPER(M187) -> Store | S187: Debit Card | T187: Furniture | U187: =IF(I187<=0,"INVALID","VALID") -> VALID | V187: =IF(I187>100,"REVIEW","NORMAL") -> NORMAL | W187: =IF(OR(K187<0,K187>1),"Invalid","Valid") -> Valid | X187: =I187*J187 -> 20042.94 | Y187: =I187*J187-(I187*J187*K187) -> 20042.94
...

Sheet Analysis
A1: Question | B1: Answer | D1: Row Labels | E1: Sum of Sales_Amount | G1: Row Labels | H1: Sum of Sales_Amount | J1: Row Labels | K1: Sum of Sales_Amount | M1: Row Labels | N1: Sum of Sales_Amount
A2: Total Sales | B2: =SUM('Clean_data '!L:L) -> 29592577 | D2: Accessories | E2: 938550.64 | G2: Ahmedabad | H2: 2196364.3 | J2: Backpack | K2: 493555.52 | M2: Anil | N2: 4769147.2
A3: Total Quantity | B3: =SUM('Clean_data '!I:I) -> 4592 | D3: Electronics | E3: 23145611 | G3: Bengaluru | H3: 2331377.7 | J3: Desk | K3: 2220172 | M3: Arjun | N3: 4459204.6
A4: Average Sales Amount | B4: =AVERAGE('Clean_data '!L:L) -> 19675.916 | D4: Furniture | E4: 5328687.6 | G4: Bhubaneswar | H4: 2131850.7 | J4: Desk Lamp | K4: 365243.49 | M4: Kiran | N4: 3401028.4
A5: Highest Sales Amount | B5: =MAX('Clean_data '!L:L) -> 339764.2 | D5: Stationery | E5: 179728.6 | G5: Chandigarh | H5: 1769005 | J5: Headphones | K5: 842475.75 | M5: Meena | N5: 2754345.2
A6: Lowest Sales Amount | B6: =MIN('Clean_data '!L:L) -> 166.5 | D6: Grand Total | E6: 29592577 | G6: Chennai | H6: 1300171.9 | J6: Keyboard | K6: 573377.51 | M6: Priya | N6: 3727292.8
A7: Completed Orders | B7: =COUNTIF('Clean_data '!O:O,"completed") -> 1026 | G7: Delhi | H7: 1193556.8 | J7: Laptop 15-inch | K7: 16702445 | M7: Rahul | N7: 2861025.3
A8: Cancelled Orders | B8: =COUNTIF('Clean_data '!O:O,"cancelled") -> 243 | G8: Hyderabad | H8: 1483606.3 | J8: Monitor 24-inch | K8: 3581792.5 | M8: Sneha | N8: 3237769.7
A9: Returned Orders | B9: =COUNTIF('Clean_data '!O:O,"returned") -> 235 | D9: Row Labels | E9: Sum of Sales_Amount | G9: Jaipur | H9: 1823153.4 | J9: Notebook Pack | K9: 117802.69 | M9: Vikram | N9: 3963068.4
D10: East | E10: 8134892.6 | G10: Kolkata | H10: 2453114.7 | J10: Office Chair | K10: 2743272.1 | M10: Grand Total | N10: 29172882
D11: North | E11: 7064448.8 | G11: Lucknow | H11: 2222621.3 | J11: Pen Set | K11: 61925.91
A12: Row Labels | B12: Sum of Sales_Amount | D12: South | E12: 7093523.5 | G12: Mumbai | H12: 1334417.7 | J12: Phone Stand | K12: 182259.21
A13: Backpack | B13: 493555.52 | D13: West | E13: 7299712.6 | G13: Patna | H13: 1591722.9 | J13: USB-C Hub | K13: 530135.43 | M13: Row Labels | N13: Sum of Sales_Amount
A14: Desk | B14: 2220172 | D14: Grand Total | E14: 29592577 | G14: Pune | H14: 2165126.5 | J14: Water Bottle | K14: 262735.91 | M14: Marketplace | N14: 9144489.5
A15: Desk Lamp | B15: 365243.49 | G15: Ranchi | H15: 1937343.7 | J15: Webcam | K15: 594958.93 | M15: Online | N15: 11563653
A16: Headphones | B16: 842475.75 | G16: Surat | H16: 1550596.6 | J16: Wireless Mouse | K16: 320425.15 | M16: Store | N16: 8884435.1
A17: Keyboard | B17: 573377.51 | G17: Visakhapatnam | H17: 1933071.1 | J17: Grand Total | K17: 29592577 | M17: Grand Total | N17: 29592577
A18: Laptop 15-inch | B18: 16702445 | G18: Grand Total | H18: 29417100
A19: Monitor 24-inch | B19: 3581792.5
A20: Office Chair | B20: 2743272.1
A21: USB-C Hub | B21: 530135.43
A22: Webcam | B22: 594958.93
A23: Grand Total | B23: 28647429
